{
"meta":{"test_sets":[],"test_metrics":[],"learn_metrics":[{"best_value":"Min","name":"Logloss"}],"launch_mode":"Train","parameters":"","iteration_count":1000,"learn_sets":["learn"],"name":"experiment"},
"iterations":[
{"learn":[0.676058877],"iteration":0,"passed_time":0.00341333101,"remaining_time":3.409917679},
{"learn":[0.6602233302],"iteration":1,"passed_time":0.006839702999,"remaining_time":3.413011797},
{"learn":[0.6459932862],"iteration":2,"passed_time":0.0113514765,"remaining_time":3.772474025},
{"learn":[0.6330532221],"iteration":3,"passed_time":0.01543039067,"remaining_time":3.842167277},
{"learn":[0.6224456943],"iteration":4,"passed_time":0.01911955295,"remaining_time":3.804791037},
{"learn":[0.6092350918],"iteration":5,"passed_time":0.02246917326,"remaining_time":3.722393036},
{"learn":[0.5962716653],"iteration":6,"passed_time":0.02596929439,"remaining_time":3.683929905},
{"learn":[0.5830551698],"iteration":7,"passed_time":0.02939771201,"remaining_time":3.64531629},
{"learn":[0.5717744195],"iteration":8,"passed_time":0.03301678972,"remaining_time":3.635515402},
{"learn":[0.5624065342],"iteration":9,"passed_time":0.03632333249,"remaining_time":3.596009916},
{"learn":[0.5533897121],"iteration":10,"passed_time":0.03966300502,"remaining_time":3.566064724},
{"learn":[0.5463429841],"iteration":11,"passed_time":0.04354423926,"remaining_time":3.585142366},
{"learn":[0.5382036093],"iteration":12,"passed_time":0.04714472237,"remaining_time":3.579372383},
{"learn":[0.5307664271],"iteration":13,"passed_time":0.05042723781,"remaining_time":3.55151832},
{"learn":[0.522576517],"iteration":14,"passed_time":0.0538012983,"remaining_time":3.532951921},
{"learn":[0.5139421862],"iteration":15,"passed_time":0.05716319368,"remaining_time":3.515536411},
{"learn":[0.5077342213],"iteration":16,"passed_time":0.06061838328,"remaining_time":3.505168868},
{"learn":[0.501720222],"iteration":17,"passed_time":0.06374776159,"remaining_time":3.477794549},
{"learn":[0.4953075841],"iteration":18,"passed_time":0.06726674517,"remaining_time":3.473088264},
{"learn":[0.4892588612],"iteration":19,"passed_time":0.07053046151,"remaining_time":3.455992614},
{"learn":[0.4844347644],"iteration":20,"passed_time":0.07375599445,"remaining_time":3.438434218},
{"learn":[0.4794973954],"iteration":21,"passed_time":0.07727450988,"remaining_time":3.435203212},
{"learn":[0.4749898277],"iteration":22,"passed_time":0.08083954427,"remaining_time":3.43392325},
{"learn":[0.469854879],"iteration":23,"passed_time":0.08398524905,"remaining_time":3.415400128},
{"learn":[0.4645460713],"iteration":24,"passed_time":0.08767946592,"remaining_time":3.419499171},
{"learn":[0.4604763894],"iteration":25,"passed_time":0.0912125268,"remaining_time":3.416961581},
{"learn":[0.4564364464],"iteration":26,"passed_time":0.09442487857,"remaining_time":3.402792846},
{"learn":[0.4529379796],"iteration":27,"passed_time":0.09769935586,"remaining_time":3.391563353},
{"learn":[0.4481883931],"iteration":28,"passed_time":0.1007581737,"remaining_time":3.37366161},
{"learn":[0.4436988541],"iteration":29,"passed_time":0.1038772496,"remaining_time":3.358697737},
{"learn":[0.4406344019],"iteration":30,"passed_time":0.1071561194,"remaining_time":3.349492895},
{"learn":[0.437076748],"iteration":31,"passed_time":0.1102194787,"remaining_time":3.334139231},
{"learn":[0.4338757404],"iteration":32,"passed_time":0.1134021814,"remaining_time":3.323027557},
{"learn":[0.4307574876],"iteration":33,"passed_time":0.117142868,"remaining_time":3.328235603},
{"learn":[0.4274063899],"iteration":34,"passed_time":0.120784074,"remaining_time":3.33018947},
{"learn":[0.4243578551],"iteration":35,"passed_time":0.1240579317,"remaining_time":3.321995727},
{"learn":[0.4214750848],"iteration":36,"passed_time":0.1274992263,"remaining_time":3.31842581},
{"learn":[0.4191457784],"iteration":37,"passed_time":0.1306217102,"remaining_time":3.306791717},
{"learn":[0.4164630465],"iteration":38,"passed_time":0.1339562118,"remaining_time":3.300818449},
{"learn":[0.4134511858],"iteration":39,"passed_time":0.1373444274,"remaining_time":3.296266257},
{"learn":[0.4108221124],"iteration":40,"passed_time":0.1405236021,"remaining_time":3.286881327},
{"learn":[0.4081448528],"iteration":41,"passed_time":0.1436241667,"remaining_time":3.275998849},
{"learn":[0.4060604067],"iteration":42,"passed_time":0.1472300143,"remaining_time":3.276723807},
{"learn":[0.4037318735],"iteration":43,"passed_time":0.150836099,"remaining_time":3.277257059},
{"learn":[0.4016543993],"iteration":44,"passed_time":0.1540031764,"remaining_time":3.268289633},
{"learn":[0.3999255868],"iteration":45,"passed_time":0.1573477595,"remaining_time":3.263255708},
{"learn":[0.3979554891],"iteration":46,"passed_time":0.1607832304,"remaining_time":3.260136566},
{"learn":[0.3955316415],"iteration":47,"passed_time":0.1641765202,"remaining_time":3.256167651},
{"learn":[0.3933304299],"iteration":48,"passed_time":0.1679647615,"remaining_time":3.259887514},
{"learn":[0.3916069621],"iteration":49,"passed_time":0.1711071692,"remaining_time":3.251036215},
{"learn":[0.3897824782],"iteration":50,"passed_time":0.1745087744,"remaining_time":3.247231899},
{"learn":[0.3880803827],"iteration":51,"passed_time":0.1775808715,"remaining_time":3.237435887},
{"learn":[0.3869892996],"iteration":52,"passed_time":0.1810110566,"remaining_time":3.234291898},
{"learn":[0.3854310631],"iteration":53,"passed_time":0.1843948124,"remaining_time":3.230323936},
{"learn":[0.3835461751],"iteration":54,"passed_time":0.187586295,"remaining_time":3.223073615},
{"learn":[0.3814000623],"iteration":55,"passed_time":0.1908126682,"remaining_time":3.216556406},
{"learn":[0.3800707882],"iteration":56,"passed_time":0.1946408327,"remaining_time":3.220110618},
{"learn":[0.3782076663],"iteration":57,"passed_time":0.1990863566,"remaining_time":3.233437034},
{"learn":[0.376827751],"iteration":58,"passed_time":0.2027532549,"remaining_time":3.233742591},
{"learn":[0.3754072148],"iteration":59,"passed_time":0.2066804956,"remaining_time":3.237994431},
{"learn":[0.3735868083],"iteration":60,"passed_time":0.2100102422,"remaining_time":3.232780614},
{"learn":[0.3723509044],"iteration":61,"passed_time":0.2139865093,"remaining_time":3.237408801},
{"learn":[0.3704766511],"iteration":62,"passed_time":0.2179899917,"remaining_time":3.242168606},
{"learn":[0.3688674488],"iteration":63,"passed_time":0.2215759074,"remaining_time":3.240547646},
{"learn":[0.3671458167],"iteration":64,"passed_time":0.2256426803,"remaining_time":3.24578317},
{"learn":[0.3657248131],"iteration":65,"passed_time":0.2294261911,"remaining_time":3.24672822},
{"learn":[0.3645805152],"iteration":66,"passed_time":0.2328687912,"remaining_time":3.242784808},
{"learn":[0.3629983335],"iteration":67,"passed_time":0.236340632,"remaining_time":3.239256897},
{"learn":[0.3618932384],"iteration":68,"passed_time":0.2396111653,"remaining_time":3.233014419},
{"learn":[0.3605167466],"iteration":69,"passed_time":0.2432986845,"remaining_time":3.232396808},
{"learn":[0.3591749384],"iteration":70,"passed_time":0.2465034936,"remaining_time":3.225376698},
{"learn":[0.3583388864],"iteration":71,"passed_time":0.2498922372,"remaining_time":3.220833279},
{"learn":[0.3574073825],"iteration":72,"passed_time":0.253154332,"remaining_time":3.21471323},
{"learn":[0.3564713409],"iteration":73,"passed_time":0.2565318121,"remaining_time":3.210114297},
{"learn":[0.3554912458],"iteration":74,"passed_time":0.2606539761,"remaining_time":3.214732372},
{"learn":[0.3536284485],"iteration":75,"passed_time":0.2643836002,"remaining_time":3.214347981},
{"learn":[0.352453215],"iteration":76,"passed_time":0.2678859895,"remaining_time":3.211152835},
{"learn":[0.3514907766],"iteration":77,"passed_time":0.2712536687,"remaining_time":3.206357469},
{"learn":[0.3504911207],"iteration":78,"passed_time":0.274891233,"remaining_time":3.204744627},
{"learn":[0.3493192017],"iteration":79,"passed_time":0.2782827784,"remaining_time":3.200251952},
{"learn":[0.3483662776],"iteration":80,"passed_time":0.2816618225,"remaining_time":3.195644628},
{"learn":[0.3473165601],"iteration":81,"passed_time":0.28482976,"remaining_time":3.188703899},
{"learn":[0.3463251502],"iteration":82,"passed_time":0.2882155782,"remaining_time":3.184261268},
{"learn":[0.3453126414],"iteration":83,"passed_time":0.2916217071,"remaining_time":3.180065282},
{"learn":[0.3442547374],"iteration":84,"passed_time":0.2947585557,"remaining_time":3.172989159},
{"learn":[0.3432296844],"iteration":85,"passed_time":0.298027345,"remaining_time":3.167406899},
{"learn":[0.3422159585],"iteration":86,"passed_time":0.3014306498,"remaining_time":3.163289463},
{"learn":[0.3413286773],"iteration":87,"passed_time":0.305201917,"remaining_time":3.163001686},
{"learn":[0.3402031082],"iteration":88,"passed_time":0.3085015528,"remaining_time":3.157808029},
{"learn":[0.3387154244],"iteration":89,"passed_time":0.312228712,"remaining_time":3.156979199},
{"learn":[0.3376042254],"iteration":90,"passed_time":0.3157105922,"remaining_time":3.153636575},
{"learn":[0.3371391845],"iteration":91,"passed_time":0.3189562574,"remaining_time":3.147959584},
{"learn":[0.3363897256],"iteration":92,"passed_time":0.3223306002,"remaining_time":3.143589832},
{"learn":[0.3353968269],"iteration":93,"passed_time":0.3255908355,"remaining_time":3.138141457},
{"learn":[0.3345688033],"iteration":94,"passed_time":0.3288521686,"remaining_time":3.132749606},
{"learn":[0.3334430872],"iteration":95,"passed_time":0.3325968215,"remaining_time":3.131953402},
{"learn":[0.3324908092],"iteration":96,"passed_time":0.335777274,"remaining_time":3.125844107},
{"learn":[0.3318043675],"iteration":97,"passed_time":0.3389178853,"remaining_time":3.119427883},
{"learn":[0.3309096973],"iteration":98,"passed_time":0.3432635173,"remaining_time":3.124044739},
{"learn":[0.3302419929],"iteration":99,"passed_time":0.3466338753,"remaining_time":3.119704878},
{"learn":[0.3294126359],"iteration":100,"passed_time":0.3500416948,"remaining_time":3.11571766},
{"learn":[0.3285017485],"iteration":101,"passed_time":0.3531774901,"remaining_time":3.109346922},
{"learn":[0.3279032382],"iteration":102,"passed_time":0.3564129406,"remaining_time":3.103906871},
{"learn":[0.3271362186],"iteration":103,"passed_time":0.3600097556,"remaining_time":3.101622509},
{"learn":[0.3265879812],"iteration":104,"passed_time":0.363821084,"remaining_time":3.101141621},
{"learn":[0.3260615029],"iteration":105,"passed_time":0.3674658868,"remaining_time":3.099193422},
{"learn":[0.3251884352],"iteration":106,"passed_time":0.3711075243,"remaining_time":3.097187095},
{"learn":[0.3244274585],"iteration":107,"passed_time":0.3743575903,"remaining_time":3.091916394},
{"learn":[0.3238319862],"iteration":108,"passed_time":0.3780054098,"remaining_time":3.089934129},
{"learn":[0.3232543956],"iteration":109,"passed_time":0.3811902163,"remaining_time":3.084175386},
{"learn":[0.3226902757],"iteration":110,"passed_time":0.3842834648,"remaining_time":3.077729732},
{"learn":[0.3219233372],"iteration":111,"passed_time":0.3874527339,"remaining_time":3.071946676},
{"learn":[0.321232322],"iteration":112,"passed_time":0.390631864,"remaining_time":3.066287286},
{"learn":[0.3206352292],"iteration":113,"passed_time":0.3940421998,"remaining_time":3.062468325},
{"learn":[0.3201289787],"iteration":114,"passed_time":0.3975824905,"remaining_time":3.059656557},
{"learn":[0.3193262051],"iteration":115,"passed_time":0.4008052791,"remaining_time":3.054412644},
{"learn":[0.3187131211],"iteration":116,"passed_time":0.4052967192,"remaining_time":3.058777804},
{"learn":[0.3178903338],"iteration":117,"passed_time":0.4122953373,"remaining_time":3.081732945},
{"learn":[0.3171474895],"iteration":118,"passed_time":0.4178087855,"remaining_time":3.093189412},
{"learn":[0.3166143084],"iteration":119,"passed_time":0.4248850071,"remaining_time":3.115823386},
{"learn":[0.3161946074],"iteration":120,"passed_time":0.4353253315,"remaining_time":3.162404681},
{"learn":[0.315605809],"iteration":121,"passed_time":0.4430118248,"remaining_time":3.188232641},
{"learn":[0.3149975984],"iteration":122,"passed_time":0.450755999,"remaining_time":3.21392692},
{"learn":[0.3143968106],"iteration":123,"passed_time":0.4557861802,"remaining_time":3.219908822},
{"learn":[0.3135439361],"iteration":124,"passed_time":0.4606173336,"remaining_time":3.224321335},
{"learn":[0.3128792854],"iteration":125,"passed_time":0.4658498075,"remaining_time":3.231370887},
{"learn":[0.3123481675],"iteration":126,"passed_time":0.4711708217,"remaining_time":3.238835648},
{"learn":[0.3116924546],"iteration":127,"passed_time":0.4747532452,"remaining_time":3.234256483},
{"learn":[0.3111849269],"iteration":128,"passed_time":0.4790035744,"remaining_time":3.234202429},
{"learn":[0.3108125461],"iteration":129,"passed_time":0.4830148551,"remaining_time":3.23248403},
{"learn":[0.3103534018],"iteration":130,"passed_time":0.4872940594,"remaining_time":3.232507921},
{"learn":[0.309851906],"iteration":131,"passed_time":0.4908936303,"remaining_time":3.227997509},
{"learn":[0.3093073813],"iteration":132,"passed_time":0.4943560716,"remaining_time":3.222606873},
{"learn":[0.3088496237],"iteration":133,"passed_time":0.4988609442,"remaining_time":3.223981923},
{"learn":[0.3085111755],"iteration":134,"passed_time":0.5028385158,"remaining_time":3.221891231},
{"learn":[0.3081264165],"iteration":135,"passed_time":0.5071013206,"remaining_time":3.221584861},
{"learn":[0.3075443668],"iteration":136,"passed_time":0.5113906197,"remaining_time":3.221387626},
{"learn":[0.3068712622],"iteration":137,"passed_time":0.5165125566,"remaining_time":3.226332056},
{"learn":[0.3064998194],"iteration":138,"passed_time":0.5205693697,"remaining_time":3.22453401},
{"learn":[0.3056528643],"iteration":139,"passed_time":0.5245569897,"remaining_time":3.222278651},
{"learn":[0.3048700027],"iteration":140,"passed_time":0.5290376623,"remaining_time":3.223002496},
{"learn":[0.3040635641],"iteration":141,"passed_time":0.5340061887,"remaining_time":3.226600774},
{"learn":[0.3034270518],"iteration":142,"passed_time":0.5381889912,"remaining_time":3.225370388},
{"learn":[0.303034823],"iteration":143,"passed_time":0.5418783399,"remaining_time":3.221165687},
{"learn":[0.3025874894],"iteration":144,"passed_time":0.546183425,"remaining_time":3.220598816},
{"learn":[0.302056189],"iteration":145,"passed_time":0.5500663045,"remaining_time":3.217511124},
{"learn":[0.3010564509],"iteration":146,"passed_time":0.5539953953,"remaining_time":3.214680763},
{"learn":[0.3006109508],"iteration":147,"passed_time":0.5571943212,"remaining_time":3.207632174},
{"learn":[0.300124065],"iteration":148,"passed_time":0.561001571,"remaining_time":3.204109644},
{"learn":[0.2997046263],"iteration":149,"passed_time":0.5649628974,"remaining_time":3.201456418},
{"learn":[0.2990724197],"iteration":150,"passed_time":0.5684348346,"remaining_time":3.196034269},
{"learn":[0.2985062643],"iteration":151,"passed_time":0.5727678244,"remaining_time":3.195441547},
{"learn":[0.2980360509],"iteration":152,"passed_time":0.5764730691,"remaining_time":3.191324768},
{"learn":[0.2974288545],"iteration":153,"passed_time":0.5801482641,"remaining_time":3.187048256},
{"learn":[0.2968788174],"iteration":154,"passed_time":0.5835831189,"remaining_time":3.181469261},
{"learn":[0.2965476883],"iteration":155,"passed_time":0.5872435449,"remaining_time":3.177138153},
{"learn":[0.2961520827],"iteration":156,"passed_time":0.5915703978,"remaining_time":3.176393919},
{"learn":[0.295688046],"iteration":157,"passed_time":0.59509826,"remaining_time":3.171346424},
{"learn":[0.2953473243],"iteration":158,"passed_time":0.5989377974,"remaining_time":3.167966589},
{"learn":[0.2948460053],"iteration":159,"passed_time":0.6027750467,"remaining_time":3.164568995},
{"learn":[0.2942884049],"iteration":160,"passed_time":0.6067773189,"remaining_time":3.162025904},
{"learn":[0.2937507128],"iteration":161,"passed_time":0.6119030466,"remaining_time":3.165276254},
{"learn":[0.2933460589],"iteration":162,"passed_time":0.6161918669,"remaining_time":3.164126335},
{"learn":[0.2928758728],"iteration":163,"passed_time":0.6213093177,"remaining_time":3.167162132},
{"learn":[0.2925098486],"iteration":164,"passed_time":0.6260717331,"remaining_time":3.168302407},
{"learn":[0.292033311],"iteration":165,"passed_time":0.6314694809,"remaining_time":3.172563537},
{"learn":[0.2914525839],"iteration":166,"passed_time":0.6362542311,"remaining_time":3.173651344},
{"learn":[0.2911885754],"iteration":167,"passed_time":0.6407225994,"remaining_time":3.173102397},
{"learn":[0.2906875994],"iteration":168,"passed_time":0.6443928455,"remaining_time":3.168582572},
{"learn":[0.2903647406],"iteration":169,"passed_time":0.6514584416,"remaining_time":3.180650038},
{"learn":[0.2895681982],"iteration":170,"passed_time":0.6578324001,"remaining_time":3.1891407},
{"learn":[0.28907673],"iteration":171,"passed_time":0.6625872729,"remaining_time":3.189664314},
{"learn":[0.2885791135],"iteration":172,"passed_time":0.6689678156,"remaining_time":3.197898171},
{"learn":[0.2879825683],"iteration":173,"passed_time":0.6740383004,"remaining_time":3.199745035},
{"learn":[0.2875351611],"iteration":174,"passed_time":0.6789338092,"remaining_time":3.200687958},
{"learn":[0.2871875366],"iteration":175,"passed_time":0.6887180332,"remaining_time":3.22445261},
{"learn":[0.2866879184],"iteration":176,"passed_time":0.6925760038,"remaining_time":3.220282775},
{"learn":[0.2862702713],"iteration":177,"passed_time":0.6997720633,"remaining_time":3.231531663},
{"learn":[0.2857776494],"iteration":178,"passed_time":0.7045744923,"remaining_time":3.231595856},
{"learn":[0.2852438137],"iteration":179,"passed_time":0.7086455912,"remaining_time":3.22827436},
{"learn":[0.284717467],"iteration":180,"passed_time":0.7141802282,"remaining_time":3.231566889},
{"learn":[0.2842985111],"iteration":181,"passed_time":0.7214901813,"remaining_time":3.242741584},
{"learn":[0.283581665],"iteration":182,"passed_time":0.7283401221,"remaining_time":3.251660545},
{"learn":[0.283253994],"iteration":183,"passed_time":0.7340329071,"remaining_time":3.25527637},
{"learn":[0.2828218714],"iteration":184,"passed_time":0.7406220087,"remaining_time":3.2627402},
{"learn":[0.2824284388],"iteration":185,"passed_time":0.7464858788,"remaining_time":3.266879061},
{"learn":[0.2816708306],"iteration":186,"passed_time":0.7523454061,"remaining_time":3.27089206},
{"learn":[0.2812823402],"iteration":187,"passed_time":0.7599144773,"remaining_time":3.282183806},
{"learn":[0.2809727961],"iteration":188,"passed_time":0.7647040859,"remaining_time":3.281349278},
{"learn":[0.2806269086],"iteration":189,"passed_time":0.769362713,"remaining_time":3.279914724},
{"learn":[0.2802169211],"iteration":190,"passed_time":0.7747666704,"remaining_time":3.281603332},
{"learn":[0.2798286766],"iteration":191,"passed_time":0.7803574629,"remaining_time":3.284004323},
{"learn":[0.2794909759],"iteration":192,"passed_time":0.7874623166,"remaining_time":3.292653313},
{"learn":[0.279217739],"iteration":193,"passed_time":0.7921462649,"remaining_time":3.291081905},
{"learn":[0.2788292416],"iteration":194,"passed_time":0.7968523865,"remaining_time":3.289570108},
{"learn":[0.2780947481],"iteration":195,"passed_time":0.8022497443,"remaining_time":3.290861196},
{"learn":[0.277805182],"iteration":196,"passed_time":0.8067058225,"remaining_time":3.288247591},
{"learn":[0.2774205539],"iteration":197,"passed_time":0.8112421915,"remaining_time":3.285940594},
{"learn":[0.2769915116],"iteration":198,"passed_time":0.8160828913,"remaining_time":3.284836161},
{"learn":[0.2765694217],"iteration":199,"passed_time":0.8208094281,"remaining_time":3.283237712},
{"learn":[0.2761695397],"iteration":200,"passed_time":0.8261057497,"remaining_time":3.283873105},
{"learn":[0.2756713645],"iteration":201,"passed_time":0.8311995294,"remaining_time":3.283649626},
{"learn":[0.2753118617],"iteration":202,"passed_time":0.8385691206,"remaining_time":3.292313247},
{"learn":[0.2749181626],"iteration":203,"passed_time":0.8462805046,"remaining_time":3.302153341},
{"learn":[0.274328223],"iteration":204,"passed_time":0.8529168445,"remaining_time":3.307653129},
{"learn":[0.2737616568],"iteration":205,"passed_time":0.8600059077,"remaining_time":3.314780052},
{"learn":[0.2734400648],"iteration":206,"passed_time":0.8700487909,"remaining_time":3.333085465},
{"learn":[0.2730966985],"iteration":207,"passed_time":0.8770454464,"remaining_time":3.3395192},
{"learn":[0.2728034027],"iteration":208,"passed_time":0.8823739933,"remaining_time":3.339511142},
{"learn":[0.272431626],"iteration":209,"passed_time":0.8886043702,"remaining_time":3.342845012},
{"learn":[0.2717779491],"iteration":210,"passed_time":0.8948532598,"remaining_time":3.34615745},
{"learn":[0.2713349747],"iteration":211,"passed_time":0.9000460896,"remaining_time":3.345454333},
{"learn":[0.2708837357],"iteration":212,"passed_time":0.9073903364,"remaining_time":3.352658191},
{"learn":[0.2706809493],"iteration":213,"passed_time":0.9145578713,"remaining_time":3.359077041},
{"learn":[0.2703020469],"iteration":214,"passed_time":0.920301724,"remaining_time":3.360171411},
{"learn":[0.2698373116],"iteration":215,"passed_time":0.9263028671,"remaining_time":3.362136333},
{"learn":[0.2695425807],"iteration":216,"passed_time":0.9317483031,"remaining_time":3.362022679},
{"learn":[0.2690433651],"iteration":217,"passed_time":0.9404318531,"remaining_time":3.37347573},
{"learn":[0.2687029949],"iteration":218,"passed_time":0.946811729,"remaining_time":3.376529499},
{"learn":[0.2683311119],"iteration":219,"passed_time":0.9531255537,"remaining_time":3.379263327},
{"learn":[0.2679675455],"iteration":220,"passed_time":0.9587586144,"remaining_time":3.379515659},
{"learn":[0.2676022724],"iteration":221,"passed_time":0.9647391063,"remaining_time":3.380932544},
{"learn":[0.2671331592],"iteration":222,"passed_time":0.9702392933,"remaining_time":3.380609556},
{"learn":[0.2667075923],"iteration":223,"passed_time":0.9760596791,"remaining_time":3.381349603},
{"learn":[0.2662305083],"iteration":224,"passed_time":0.9823063883,"remaining_time":3.383499782},
{"learn":[0.2657191534],"iteration":225,"passed_time":0.9881112978,"remaining_time":3.384062586},
{"learn":[0.2655257584],"iteration":226,"passed_time":0.9964138039,"remaining_time":3.393074319},
{"learn":[0.2650793467],"iteration":227,"passed_time":1.001101535,"remaining_time":3.389694671},
{"learn":[0.2646973936],"iteration":228,"passed_time":1.006672549,"remaining_time":3.389277446},
{"learn":[0.2642612485],"iteration":229,"passed_time":1.01529857,"remaining_time":3.399043038},
{"learn":[0.2639234212],"iteration":230,"passed_time":1.021494054,"remaining_time":3.400558126},
{"learn":[0.2635348938],"iteration":231,"passed_time":1.02758928,"remaining_time":3.401674857},
{"learn":[0.2631200318],"iteration":232,"passed_time":1.033168662,"remaining_time":3.401031604},
{"learn":[0.2627552375],"iteration":233,"passed_time":1.039127956,"remaining_time":3.401589806},
{"learn":[0.2625505212],"iteration":234,"passed_time":1.043385428,"remaining_time":3.396552562},
{"learn":[0.2622668661],"iteration":235,"passed_time":1.049535813,"remaining_time":3.397649836},
{"learn":[0.2618368696],"iteration":236,"passed_time":1.054259799,"remaining_time":3.394093783},
{"learn":[0.2613279748],"iteration":237,"passed_time":1.060209615,"remaining_time":3.394452633},
{"learn":[0.2609717917],"iteration":238,"passed_time":1.065432715,"remaining_time":3.392444754},
{"learn":[0.2606052336],"iteration":239,"passed_time":1.069559592,"remaining_time":3.386938707},
{"learn":[0.260186766],"iteration":240,"passed_time":1.07401669,"remaining_time":3.382484097},
{"learn":[0.2598470845],"iteration":241,"passed_time":1.079298689,"remaining_time":3.380613248},
{"learn":[0.2596085709],"iteration":242,"passed_time":1.083889473,"remaining_time":3.376561032},
{"learn":[0.2593360954],"iteration":243,"passed_time":1.091300336,"remaining_time":3.381242025},
{"learn":[0.2590577509],"iteration":244,"passed_time":1.096451729,"remaining_time":3.37886145},
{"learn":[0.2589839834],"iteration":245,"passed_time":1.100804075,"remaining_time":3.374009238},
{"learn":[0.2586671851],"iteration":246,"passed_time":1.105889489,"remaining_time":3.37139589},
{"learn":[0.2584263013],"iteration":247,"passed_time":1.110241879,"remaining_time":3.36653989},
{"learn":[0.2579943323],"iteration":248,"passed_time":1.114234612,"remaining_time":3.360603187},
{"learn":[0.2577669715],"iteration":249,"passed_time":1.121825716,"remaining_time":3.365477147},
{"learn":[0.2574776613],"iteration":250,"passed_time":1.127685348,"remaining_time":3.365084964},
{"learn":[0.2571241257],"iteration":251,"passed_time":1.132534313,"remaining_time":3.361649468},
{"learn":[0.2569208506],"iteration":252,"passed_time":1.136557066,"remaining_time":3.355763354},
{"learn":[0.2564398022],"iteration":253,"passed_time":1.140138032,"remaining_time":3.348594376},
{"learn":[0.2560978727],"iteration":254,"passed_time":1.144585011,"remaining_time":3.34398366},
{"learn":[0.255756657],"iteration":255,"passed_time":1.150121907,"remaining_time":3.342541791},
{"learn":[0.2555387816],"iteration":256,"passed_time":1.154497747,"remaining_time":3.337711386},
{"learn":[0.2552282434],"iteration":257,"passed_time":1.159505026,"remaining_time":3.334700501},
{"learn":[0.2549760509],"iteration":258,"passed_time":1.16339067,"remaining_time":3.328465198},
{"learn":[0.2547292102],"iteration":259,"passed_time":1.167796071,"remaining_time":3.323727278},
{"learn":[0.2544216797],"iteration":260,"passed_time":1.171835932,"remaining_time":3.31795691},
{"learn":[0.2541834477],"iteration":261,"passed_time":1.176050606,"remaining_time":3.312692164},
{"learn":[0.2535882297],"iteration":262,"passed_time":1.180431902,"remaining_time":3.307902326},
{"learn":[0.2533202666],"iteration":263,"passed_time":1.184801554,"remaining_time":3.303083121},
{"learn":[0.2529462295],"iteration":264,"passed_time":1.188686198,"remaining_time":3.296922096},
{"learn":[0.2526660595],"iteration":265,"passed_time":1.192983314,"remaining_time":3.291916363},
{"learn":[0.2524424984],"iteration":266,"passed_time":1.197448576,"remaining_time":3.287377552},
{"learn":[0.2520725718],"iteration":267,"passed_time":1.202040785,"remaining_time":3.283186024},
{"learn":[0.2517451452],"iteration":268,"passed_time":1.207505893,"remaining_time":3.281363597},
{"learn":[0.2512305155],"iteration":269,"passed_time":1.211774474,"remaining_time":3.276279133},
{"learn":[0.2509555688],"iteration":270,"passed_time":1.215570657,"remaining_time":3.269929922},
{"learn":[0.2507527662],"iteration":271,"passed_time":1.219211382,"remaining_time":3.263183404},
{"learn":[0.2503311532],"iteration":272,"passed_time":1.222968204,"remaining_time":3.256768807},
{"learn":[0.25005788],"iteration":273,"passed_time":1.22903201,"remaining_time":3.256486275},
{"learn":[0.2497688407],"iteration":274,"passed_time":1.233841094,"remaining_time":3.252853793},
{"learn":[0.2493637878],"iteration":275,"passed_time":1.240545324,"remaining_time":3.25418411},
{"learn":[0.249209271],"iteration":276,"passed_time":1.2469437,"remaining_time":3.254658105},
{"learn":[0.2489098008],"iteration":277,"passed_time":1.25434177,"remaining_time":3.257678986},
{"learn":[0.2486319085],"iteration":278,"passed_time":1.260470217,"remaining_time":3.257344181},
{"learn":[0.2480656169],"iteration":279,"passed_time":1.266611783,"remaining_time":3.257001727},
{"learn":[0.2478127482],"iteration":280,"passed_time":1.273056846,"remaining_time":3.257394564},
{"learn":[0.2476435431],"iteration":281,"passed_time":1.278686577,"remaining_time":3.255662987},
{"learn":[0.2473173282],"iteration":282,"passed_time":1.285145324,"remaining_time":3.256004231},
{"learn":[0.2470328467],"iteration":283,"passed_time":1.291124548,"remaining_time":3.255088649},
{"learn":[0.2467832894],"iteration":284,"passed_time":1.303979027,"remaining_time":3.271385979},
{"learn":[0.2464875526],"iteration":285,"passed_time":1.311332958,"remaining_time":3.273747315},
{"learn":[0.246214782],"iteration":286,"passed_time":1.320931038,"remaining_time":3.281616132},
{"learn":[0.2453689905],"iteration":287,"passed_time":1.333606637,"remaining_time":3.296971963},
{"learn":[0.2451297035],"iteration":288,"passed_time":1.354800532,"remaining_time":3.333090583},
{"learn":[0.2448099078],"iteration":289,"passed_time":1.366244963,"remaining_time":3.344944564},
{"learn":[0.2445424958],"iteration":290,"passed_time":1.376052537,"remaining_time":3.35265034},
{"learn":[0.2442495984],"iteration":291,"passed_time":1.384147048,"remaining_time":3.356082569},
{"learn":[0.2440105953],"iteration":292,"passed_time":1.391266883,"remaining_time":3.357084253},
{"learn":[0.2436062028],"iteration":293,"passed_time":1.399827296,"remaining_time":3.361490037},
{"learn":[0.2432436559],"iteration":294,"passed_time":1.407661374,"remaining_time":3.364072098},
{"learn":[0.2429920926],"iteration":295,"passed_time":1.425351733,"remaining_time":3.390025744},
{"learn":[0.2425822043],"iteration":296,"passed_time":1.43884132,"remaining_time":3.40574225},
{"learn":[0.2422200374],"iteration":297,"passed_time":1.453050668,"remaining_time":3.422958286},
{"learn":[0.2418281488],"iteration":298,"passed_time":1.459181322,"remaining_time":3.421023769},
{"learn":[0.2414663347],"iteration":299,"passed_time":1.473329574,"remaining_time":3.437769006},
{"learn":[0.2409795179],"iteration":300,"passed_time":1.485221224,"remaining_time":3.449068557},
{"learn":[0.2405552269],"iteration":301,"passed_time":1.494582052,"remaining_time":3.45436514},
{"learn":[0.2400416643],"iteration":302,"passed_time":1.502656938,"remaining_time":3.456606884},
{"learn":[0.2397051781],"iteration":303,"passed_time":1.508220514,"remaining_time":3.453031177},
{"learn":[0.2393189117],"iteration":304,"passed_time":1.514498991,"remaining_time":3.45107147},
{"learn":[0.2390030379],"iteration":305,"passed_time":1.521448305,"remaining_time":3.450604979},
{"learn":[0.238702964],"iteration":306,"passed_time":1.527605822,"remaining_time":3.448308907},
{"learn":[0.2384551535],"iteration":307,"passed_time":1.533365522,"remaining_time":3.445093966},
{"learn":[0.2381769809],"iteration":308,"passed_time":1.541805777,"remaining_time":3.447856931},
{"learn":[0.2379860526],"iteration":309,"passed_time":1.547231427,"remaining_time":3.443837693},
{"learn":[0.237745861],"iteration":310,"passed_time":1.552202964,"remaining_time":3.438803352},
{"learn":[0.2374771351],"iteration":311,"passed_time":1.558526457,"remaining_time":3.43675065},
{"learn":[0.2373042116],"iteration":312,"passed_time":1.563041793,"remaining_time":3.430701954},
{"learn":[0.2370918512],"iteration":313,"passed_time":1.573582979,"remaining_time":3.437827782},
{"learn":[0.2367557304],"iteration":314,"passed_time":1.581520632,"remaining_time":3.439179787},
{"learn":[0.2364173008],"iteration":315,"passed_time":1.588432921,"remaining_time":3.438253538},
{"learn":[0.2361882819],"iteration":316,"passed_time":1.595179562,"remaining_time":3.436932621},
{"learn":[0.2358439712],"iteration":317,"passed_time":1.601783941,"remaining_time":3.435272477},
{"learn":[0.2355110501],"iteration":318,"passed_time":1.606987858,"remaining_time":3.430591635},
{"learn":[0.2351338442],"iteration":319,"passed_time":1.611311073,"remaining_time":3.424036031},
{"learn":[0.2348692147],"iteration":320,"passed_time":1.620091895,"remaining_time":3.426923355},
{"learn":[0.2346856623],"iteration":321,"passed_time":1.628485598,"remaining_time":3.428923091},
{"learn":[0.234347154],"iteration":322,"passed_time":1.63829378,"remaining_time":3.433823185},
{"learn":[0.234044933],"iteration":323,"passed_time":1.644669494,"remaining_time":3.43147092},
{"learn":[0.2338481008],"iteration":324,"passed_time":1.655508974,"remaining_time":3.438364792},
{"learn":[0.2334529838],"iteration":325,"passed_time":1.662883244,"remaining_time":3.437985603},
{"learn":[0.2330635666],"iteration":326,"passed_time":1.668367898,"remaining_time":3.433674603},
{"learn":[0.2327339606],"iteration":327,"passed_time":1.673897627,"remaining_time":3.429448796},
{"learn":[0.2323706549],"iteration":328,"passed_time":1.68011507,"remaining_time":3.426617665},
{"learn":[0.2321971738],"iteration":329,"passed_time":1.685538139,"remaining_time":3.42215319},
{"learn":[0.2319959134],"iteration":330,"passed_time":1.690230017,"remaining_time":3.41620508},
{"learn":[0.2318029877],"iteration":331,"passed_time":1.697062488,"remaining_time":3.414571512},
{"learn":[0.2315662476],"iteration":332,"passed_time":1.702789322,"remaining_time":3.410692125},
{"learn":[0.2313640887],"iteration":333,"passed_time":1.708359209,"remaining_time":3.406488723},
{"learn":[0.2310918728],"iteration":334,"passed_time":1.714145506,"remaining_time":3.40270675},
{"learn":[0.2305090089],"iteration":335,"passed_time":1.719109003,"remaining_time":3.39728684},
{"learn":[0.2303308024],"iteration":336,"passed_time":1.724605865,"remaining_time":3.392918956},
{"learn":[0.229942751],"iteration":337,"passed_time":1.732199329,"remaining_time":3.392650757},
{"learn":[0.2295708866],"iteration":338,"passed_time":1.738029076,"remaining_time":3.388900353},
{"learn":[0.2291597467],"iteration":339,"passed_time":1.744746249,"remaining_time":3.386860365},
{"learn":[0.2289910315],"iteration":340,"passed_time":1.75037028,"remaining_time":3.382680394},
{"learn":[0.2288515059],"iteration":341,"passed_time":1.756090997,"remaining_time":3.378678001},
{"learn":[0.2286500973],"iteration":342,"passed_time":1.767230545,"remaining_time":3.385045097},
{"learn":[0.2284112882],"iteration":343,"passed_time":1.773333418,"remaining_time":3.381705588},
{"learn":[0.2282233733],"iteration":344,"passed_time":1.777588648,"remaining_time":3.374842215},
{"learn":[0.2279180159],"iteration":345,"passed_time":1.783037129,"remaining_time":3.370249371},
{"learn":[0.2276320466],"iteration":346,"passed_time":1.788655028,"remaining_time":3.365970412},
{"learn":[0.2272647083],"iteration":347,"passed_time":1.793749669,"remaining_time":3.360703403},
{"learn":[0.227052343],"iteration":348,"passed_time":1.799156482,"remaining_time":3.356019685},
{"learn":[0.2267496648],"iteration":349,"passed_time":1.804248786,"remaining_time":3.350747745},
{"learn":[0.2265658563],"iteration":350,"passed_time":1.810832202,"remaining_time":3.3482339},
{"learn":[0.2260368453],"iteration":351,"passed_time":1.817704729,"remaining_time":3.34622916},
{"learn":[0.2258826044],"iteration":352,"passed_time":1.82315154,"remaining_time":3.3415837},
{"learn":[0.2253938126],"iteration":353,"passed_time":1.830030786,"remaining_time":3.339547705},
{"learn":[0.2251143432],"iteration":354,"passed_time":1.834992556,"remaining_time":3.33400056},
{"learn":[0.2249018658],"iteration":355,"passed_time":1.84143658,"remaining_time":3.331138083},
{"learn":[0.224573469],"iteration":356,"passed_time":1.846651103,"remaining_time":3.326041062},
{"learn":[0.2243904165],"iteration":357,"passed_time":1.851281543,"remaining_time":3.319895951},
{"learn":[0.224053044],"iteration":358,"passed_time":1.856652649,"remaining_time":3.315081749},
{"learn":[0.2237995032],"iteration":359,"passed_time":1.860841728,"remaining_time":3.308163072},
{"learn":[0.2234241024],"iteration":360,"passed_time":1.867716276,"remaining_time":3.30601302},
{"learn":[0.2230897549],"iteration":361,"passed_time":1.87436654,"remaining_time":3.303441581},
{"learn":[0.2225455343],"iteration":362,"passed_time":1.879684369,"remaining_time":3.298509486},
{"learn":[0.2222548232],"iteration":363,"passed_time":1.884922361,"remaining_time":3.293435774},
{"learn":[0.2220320213],"iteration":364,"passed_time":1.890639129,"remaining_time":3.2891941},
{"learn":[0.2217045121],"iteration":365,"passed_time":1.896447917,"remaining_time":3.285103768},
{"learn":[0.2215065028],"iteration":366,"passed_time":1.90164639,"remaining_time":3.279951404},
{"learn":[0.2212815957],"iteration":367,"passed_time":1.907723067,"remaining_time":3.276307006},
{"learn":[0.2207982257],"iteration":368,"passed_time":1.91436153,"remaining_time":3.273610096},
{"learn":[0.220662293],"iteration":369,"passed_time":1.920810303,"remaining_time":3.270568895},
{"learn":[0.2203688266],"iteration":370,"passed_time":1.926829258,"remaining_time":3.266780602},
{"learn":[0.2199843694],"iteration":371,"passed_time":1.932494143,"remaining_time":3.262382586},
{"learn":[0.2195081728],"iteration":372,"passed_time":1.936944336,"remaining_time":3.255935921},
{"learn":[0.2193453995],"iteration":373,"passed_time":1.944320012,"remaining_time":3.254396598},
{"learn":[0.2190878632],"iteration":374,"passed_time":1.949931063,"remaining_time":3.249885105},
{"learn":[0.2188295372],"iteration":375,"passed_time":1.955229121,"remaining_time":3.244848329},
{"learn":[0.2185074679],"iteration":376,"passed_time":1.960995308,"remaining_time":3.240583758},
{"learn":[0.2182870863],"iteration":377,"passed_time":1.967705684,"remaining_time":3.237864908},
{"learn":[0.2181339344],"iteration":378,"passed_time":1.975088012,"remaining_time":3.236226004},
{"learn":[0.2179281677],"iteration":379,"passed_time":1.985087993,"remaining_time":3.238827778},
{"learn":[0.2177250964],"iteration":380,"passed_time":1.990453186,"remaining_time":3.233833392},
{"learn":[0.2173851568],"iteration":381,"passed_time":1.99687779,"remaining_time":3.230550979},
{"learn":[0.2171578951],"iteration":382,"passed_time":2.004455492,"remaining_time":3.229109761},
{"learn":[0.2167201181],"iteration":383,"passed_time":2.009192931,"remaining_time":3.223080327},
{"learn":[0.2165293818],"iteration":384,"passed_time":2.014828818,"remaining_time":3.218492787},
{"learn":[0.2160773057],"iteration":385,"passed_time":2.021036609,"remaining_time":3.214809529},
{"learn":[0.2159530096],"iteration":386,"passed_time":2.027065884,"remaining_time":3.210830457},
{"learn":[0.2154560722],"iteration":387,"passed_time":2.034547621,"remaining_time":3.209131815},
{"learn":[0.2151003149],"iteration":388,"passed_time":2.04154296,"remaining_time":3.206639457},
{"learn":[0.2145464217],"iteration":389,"passed_time":2.048697038,"remaining_time":3.204372291},
{"learn":[0.2140792482],"iteration":390,"passed_time":2.058450782,"remaining_time":3.206129223},
{"learn":[0.2138407146],"iteration":391,"passed_time":2.071054937,"remaining_time":3.212248474},
{"learn":[0.2133731654],"iteration":392,"passed_time":2.076696678,"remaining_time":3.207518788},
{"learn":[0.2130399178],"iteration":393,"passed_time":2.082697971,"remaining_time":3.203337488},
{"learn":[0.2127985721],"iteration":394,"passed_time":2.089011275,"remaining_time":3.199624865},
{"learn":[0.2125668091],"iteration":395,"passed_time":2.0950104,"remaining_time":3.195419904},
{"learn":[0.2119803697],"iteration":396,"passed_time":2.101939766,"remaining_time":3.192618839},
{"learn":[0.2116945554],"iteration":397,"passed_time":2.107805815,"remaining_time":3.188188695},
{"learn":[0.2114305415],"iteration":398,"passed_time":2.114673167,"remaining_time":3.185259583},
{"learn":[0.211104821],"iteration":399,"passed_time":2.12084298,"remaining_time":3.18126447},
{"learn":[0.2109480272],"iteration":400,"passed_time":2.127904642,"remaining_time":3.178590724},
{"learn":[0.2107712357],"iteration":401,"passed_time":2.138478537,"remaining_time":3.181119813},
{"learn":[0.2106028479],"iteration":402,"passed_time":2.145287295,"remaining_time":3.178006241},
{"learn":[0.2101768845],"iteration":403,"passed_time":2.151120266,"remaining_time":3.173434847},
{"learn":[0.2097424324],"iteration":404,"passed_time":2.158407174,"remaining_time":3.170993256},
{"learn":[0.2093580397],"iteration":405,"passed_time":2.163880909,"remaining_time":3.165875024},
{"learn":[0.20885762],"iteration":406,"passed_time":2.172305426,"remaining_time":3.165054342},
{"learn":[0.208645913],"iteration":407,"passed_time":2.179424674,"remaining_time":3.162302468},
{"learn":[0.2081889],"iteration":408,"passed_time":2.187642047,"remaining_time":3.161116015},
{"learn":[0.2078687227],"iteration":409,"passed_time":2.193229943,"remaining_time":3.156111382},
{"learn":[0.2076752909],"iteration":410,"passed_time":2.200198693,"remaining_time":3.153082798},
{"learn":[0.207460417],"iteration":411,"passed_time":2.208481268,"remaining_time":3.151910159},
{"learn":[0.2069761236],"iteration":412,"passed_time":2.215031987,"remaining_time":3.148241589},
{"learn":[0.2067704696],"iteration":413,"passed_time":2.222304176,"remaining_time":3.145580307},
{"learn":[0.2065990483],"iteration":414,"passed_time":2.229740148,"remaining_time":3.143127678},
{"learn":[0.2063993735],"iteration":415,"passed_time":2.23540805,"remaining_time":3.138168993},
{"learn":[0.206201892],"iteration":416,"passed_time":2.24175528,"remaining_time":3.134156662},
{"learn":[0.2060171067],"iteration":417,"passed_time":2.25581699,"remaining_time":3.140874374},
{"learn":[0.2055455278],"iteration":418,"passed_time":2.261122037,"remaining_time":3.135350605},
{"learn":[0.2052534582],"iteration":419,"passed_time":2.265581681,"remaining_time":3.128660417},
{"learn":[0.2050372398],"iteration":420,"passed_time":2.270805245,"remaining_time":3.123031441},
{"learn":[0.2047975899],"iteration":421,"passed_time":2.275395712,"remaining_time":3.116537255},
{"learn":[0.2043513035],"iteration":422,"passed_time":2.280554962,"remaining_time":3.110827927},
{"learn":[0.2041123809],"iteration":423,"passed_time":2.284478126,"remaining_time":3.103441983},
{"learn":[0.2035756995],"iteration":424,"passed_time":2.289701608,"remaining_time":3.097831587},
{"learn":[0.2032103708],"iteration":425,"passed_time":2.294853968,"remaining_time":3.092127177},
{"learn":[0.2029956205],"iteration":426,"passed_time":2.299743348,"remaining_time":3.086072455},
{"learn":[0.202811719],"iteration":427,"passed_time":2.303550733,"remaining_time":3.078577148},
{"learn":[0.2025068724],"iteration":428,"passed_time":2.308279757,"remaining_time":3.072325737},
{"learn":[0.2019192019],"iteration":429,"passed_time":2.311831659,"remaining_time":3.064521037},
{"learn":[0.2015923206],"iteration":430,"passed_time":2.316282276,"remaining_time":3.05792254},
{"learn":[0.20122686],"iteration":431,"passed_time":2.320830894,"remaining_time":3.051462843},
{"learn":[0.2008860395],"iteration":432,"passed_time":2.325912411,"remaining_time":3.045709786},
{"learn":[0.2006859695],"iteration":433,"passed_time":2.33131858,"remaining_time":3.040383217},
{"learn":[0.2005150344],"iteration":434,"passed_time":2.335654204,"remaining_time":3.033665805},
{"learn":[0.2000295421],"iteration":435,"passed_time":2.340476576,"remaining_time":3.027588965},
{"learn":[0.1996218796],"iteration":436,"passed_time":2.344109048,"remaining_time":3.019984884},
{"learn":[0.1992892486],"iteration":437,"passed_time":2.349055311,"remaining_time":3.014084669},
{"learn":[0.1989473408],"iteration":438,"passed_time":2.353882812,"remaining_time":3.008037033},
{"learn":[0.1986390411],"iteration":439,"passed_time":2.358772039,"remaining_time":3.002073504},
{"learn":[0.1984963423],"iteration":440,"passed_time":2.36258924,"remaining_time":2.994755975},
{"learn":[0.1981598952],"iteration":441,"passed_time":2.36763065,"remaining_time":2.98899978},
{"learn":[0.197811069],"iteration":442,"passed_time":2.371668461,"remaining_time":2.98198495},
{"learn":[0.1975745918],"iteration":443,"passed_time":2.375973552,"remaining_time":2.975318232},
{"learn":[0.1971352058],"iteration":444,"passed_time":2.380463467,"remaining_time":2.968892639},
{"learn":[0.1968752185],"iteration":445,"passed_time":2.384786289,"remaining_time":2.962268171},
{"learn":[0.1965443678],"iteration":446,"passed_time":2.389028409,"remaining_time":2.955554162},
{"learn":[0.1961348012],"iteration":447,"passed_time":2.393832971,"remaining_time":2.949544197},
{"learn":[0.1958023267],"iteration":448,"passed_time":2.397817081,"remaining_time":2.942532765},
{"learn":[0.1955442656],"iteration":449,"passed_time":2.402459957,"remaining_time":2.936339947},
{"learn":[0.195320847],"iteration":450,"passed_time":2.407572057,"remaining_time":2.930725187},
{"learn":[0.1951551324],"iteration":451,"passed_time":2.411814083,"remaining_time":2.924057782},
{"learn":[0.194812494],"iteration":452,"passed_time":2.416084652,"remaining_time":2.917435551},
{"learn":[0.1945322752],"iteration":453,"passed_time":2.420761165,"remaining_time":2.911311885},
{"learn":[0.1943683372],"iteration":454,"passed_time":2.42468335,"remaining_time":2.904291046},
{"learn":[0.1940528528],"iteration":455,"passed_time":2.428961637,"remaining_time":2.89770862},
{"learn":[0.1937823425],"iteration":456,"passed_time":2.435084997,"remaining_time":2.893328563},
{"learn":[0.193542298],"iteration":457,"passed_time":2.438932102,"remaining_time":2.88624716},
{"learn":[0.1932759769],"iteration":458,"passed_time":2.445303681,"remaining_time":2.882155319},
{"learn":[0.1929604173],"iteration":459,"passed_time":2.449831562,"remaining_time":2.875889225},
{"learn":[0.1927764175],"iteration":460,"passed_time":2.45588295,"remaining_time":2.871411953},
{"learn":[0.1925876345],"iteration":461,"passed_time":2.460627861,"remaining_time":2.86540647},
{"learn":[0.1923919056],"iteration":462,"passed_time":2.46492831,"remaining_time":2.858890934},
{"learn":[0.1921477628],"iteration":463,"passed_time":2.468996555,"remaining_time":2.85211671},
{"learn":[0.1919202976],"iteration":464,"passed_time":2.472833626,"remaining_time":2.84508815},
{"learn":[0.1916907859],"iteration":465,"passed_time":2.476146924,"remaining_time":2.837473085},
{"learn":[0.1914345703],"iteration":466,"passed_time":2.479736268,"remaining_time":2.830191501},
{"learn":[0.1912931674],"iteration":467,"passed_time":2.482887194,"remaining_time":2.822427323},
{"learn":[0.1909726932],"iteration":468,"passed_time":2.486138755,"remaining_time":2.814796757},
{"learn":[0.1908360261],"iteration":469,"passed_time":2.489324415,"remaining_time":2.80711051},
{"learn":[0.1906588655],"iteration":470,"passed_time":2.49278834,"remaining_time":2.799755906},
{"learn":[0.1904890081],"iteration":471,"passed_time":2.496195198,"remaining_time":2.792353951},
{"learn":[0.1898683831],"iteration":472,"passed_time":2.499763294,"remaining_time":2.785148533},
{"learn":[0.1893790565],"iteration":473,"passed_time":2.502930263,"remaining_time":2.77751333},
{"learn":[0.1890606871],"iteration":474,"passed_time":2.506225589,"remaining_time":2.770038809},
{"learn":[0.1888136124],"iteration":475,"passed_time":2.509948771,"remaining_time":2.763052848},
{"learn":[0.1886189853],"iteration":476,"passed_time":2.513175779,"remaining_time":2.755536546},
{"learn":[0.1883936401],"iteration":477,"passed_time":2.516178035,"remaining_time":2.747792749},
{"learn":[0.1880507292],"iteration":478,"passed_time":2.519753097,"remaining_time":2.740691782},
{"learn":[0.187856646],"iteration":479,"passed_time":2.52285157,"remaining_time":2.7330892},
{"learn":[0.1877061213],"iteration":480,"passed_time":2.526365651,"remaining_time":2.72595379},
{"learn":[0.1873738687],"iteration":481,"passed_time":2.529960118,"remaining_time":2.718919795},
{"learn":[0.1870633758],"iteration":482,"passed_time":2.533299223,"remaining_time":2.711626704},
{"learn":[0.1867577743],"iteration":483,"passed_time":2.536463266,"remaining_time":2.704163316},
{"learn":[0.1863103243],"iteration":484,"passed_time":2.539958922,"remaining_time":2.697069783},
{"learn":[0.1860836727],"iteration":485,"passed_time":2.543221233,"remaining_time":2.689744267},
{"learn":[0.1859553588],"iteration":486,"passed_time":2.546458135,"remaining_time":2.682408672},
{"learn":[0.1856752041],"iteration":487,"passed_time":2.549724504,"remaining_time":2.675120791},
{"learn":[0.1854081934],"iteration":488,"passed_time":2.553267783,"remaining_time":2.668138727},
{"learn":[0.1849667757],"iteration":489,"passed_time":2.556872739,"remaining_time":2.661234892},
{"learn":[0.1847348167],"iteration":490,"passed_time":2.560916255,"remaining_time":2.654799132},
{"learn":[0.1846200823],"iteration":491,"passed_time":2.563996681,"remaining_time":2.647378687},
{"learn":[0.18432754],"iteration":492,"passed_time":2.567333121,"remaining_time":2.640239133},
{"learn":[0.1841033788],"iteration":493,"passed_time":2.570596387,"remaining_time":2.633040024},
{"learn":[0.1836223491],"iteration":494,"passed_time":2.574043228,"remaining_time":2.626044101},
{"learn":[0.1833777886],"iteration":495,"passed_time":2.577309382,"remaining_time":2.618878888},
{"learn":[0.183044161],"iteration":496,"passed_time":2.580517675,"remaining_time":2.611670806},
{"learn":[0.182912214],"iteration":497,"passed_time":2.583540071,"remaining_time":2.604291397},
{"learn":[0.182650396],"iteration":498,"passed_time":2.586632048,"remaining_time":2.59699931},
{"learn":[0.1823476613],"iteration":499,"passed_time":2.590154105,"remaining_time":2.590154105},
{"learn":[0.182124417],"iteration":500,"passed_time":2.593596859,"remaining_time":2.583243179},
{"learn":[0.1819096473],"iteration":501,"passed_time":2.597002793,"remaining_time":2.576309544},
{"learn":[0.181792258],"iteration":502,"passed_time":2.600345099,"remaining_time":2.569327066},
{"learn":[0.1814898098],"iteration":503,"passed_time":2.604008895,"remaining_time":2.56267542},
{"learn":[0.1812136725],"iteration":504,"passed_time":2.608353086,"remaining_time":2.55670253},
{"learn":[0.1810522499],"iteration":505,"passed_time":2.611779153,"remaining_time":2.549839727},
{"learn":[0.1809262538],"iteration":506,"passed_time":2.615019851,"remaining_time":2.54281023},
{"learn":[0.1805768613],"iteration":507,"passed_time":2.618373483,"remaining_time":2.535905027},
{"learn":[0.1804165416],"iteration":508,"passed_time":2.621585047,"remaining_time":2.528876735},
{"learn":[0.1802841772],"iteration":509,"passed_time":2.624897952,"remaining_time":2.521960778},
{"learn":[0.1800564139],"iteration":510,"passed_time":2.628432106,"remaining_time":2.515270646},
{"learn":[0.1798103898],"iteration":511,"passed_time":2.631552612,"remaining_time":2.508198583},
{"learn":[0.1795539509],"iteration":512,"passed_time":2.634691387,"remaining_time":2.50115927},
{"learn":[0.1793682476],"iteration":513,"passed_time":2.637775734,"remaining_time":2.494083671},
{"learn":[0.1792240085],"iteration":514,"passed_time":2.640867787,"remaining_time":2.487030828},
{"learn":[0.1789411083],"iteration":515,"passed_time":2.643902355,"remaining_time":2.479939418},
{"learn":[0.178814786],"iteration":516,"passed_time":2.647688243,"remaining_time":2.473565611},
{"learn":[0.1786600962],"iteration":517,"passed_time":2.650952639,"remaining_time":2.466716548},
{"learn":[0.1784943488],"iteration":518,"passed_time":2.654186586,"remaining_time":2.459853079},
{"learn":[0.1781822193],"iteration":519,"passed_time":2.657607971,"remaining_time":2.453176588},
{"learn":[0.1779533765],"iteration":520,"passed_time":2.661011867,"remaining_time":2.446496515},
{"learn":[0.1776056433],"iteration":521,"passed_time":2.66430674,"remaining_time":2.43972916},
{"learn":[0.1773289359],"iteration":522,"passed_time":2.667682851,"remaining_time":2.433049178},
{"learn":[0.1771079431],"iteration":523,"passed_time":2.670833651,"remaining_time":2.426177133},
{"learn":[0.1769763005],"iteration":524,"passed_time":2.674067255,"remaining_time":2.419394183},
{"learn":[0.1767086745],"iteration":525,"passed_time":2.677420638,"remaining_time":2.412732666},
{"learn":[0.1765900863],"iteration":526,"passed_time":2.68081594,"remaining_time":2.406121328},
{"learn":[0.1764884816],"iteration":527,"passed_time":2.68385666,"remaining_time":2.399205196},
{"learn":[0.176381647],"iteration":528,"passed_time":2.687133133,"remaining_time":2.392513621},
{"learn":[0.1762162389],"iteration":529,"passed_time":2.690610238,"remaining_time":2.386012852},
{"learn":[0.1760993981],"iteration":530,"passed_time":2.693832882,"remaining_time":2.379298722},
{"learn":[0.1755912929],"iteration":531,"passed_time":2.697207462,"remaining_time":2.372731376},
{"learn":[0.1754095509],"iteration":532,"passed_time":2.700402567,"remaining_time":2.366018759},
{"learn":[0.1752407077],"iteration":533,"passed_time":2.703935848,"remaining_time":2.35961443},
{"learn":[0.1750656555],"iteration":534,"passed_time":2.707312432,"remaining_time":2.353084637},
{"learn":[0.1749345359],"iteration":535,"passed_time":2.710658198,"remaining_time":2.346539933},
{"learn":[0.1746975243],"iteration":536,"passed_time":2.713864811,"remaining_time":2.339887165},
{"learn":[0.1744940131],"iteration":537,"passed_time":2.717303455,"remaining_time":2.333446462},
{"learn":[0.1742392677],"iteration":538,"passed_time":2.720350713,"remaining_time":2.326682149},
{"learn":[0.1740606886],"iteration":539,"passed_time":2.723640281,"remaining_time":2.320138017},
{"learn":[0.1739271084],"iteration":540,"passed_time":2.726873768,"remaining_time":2.313558336},
{"learn":[0.173804839],"iteration":541,"passed_time":2.730185498,"remaining_time":2.307057118},
{"learn":[0.1735125528],"iteration":542,"passed_time":2.733339467,"remaining_time":2.300434874},
{"learn":[0.173295453],"iteration":543,"passed_time":2.736657748,"remaining_time":2.293963112},
{"learn":[0.1729971976],"iteration":544,"passed_time":2.740028228,"remaining_time":2.287546502},
{"learn":[0.1727208665],"iteration":545,"passed_time":2.743612369,"remaining_time":2.28131871},
{"learn":[0.1725104208],"iteration":546,"passed_time":2.746797904,"remaining_time":2.274770477},
{"learn":[0.172304535],"iteration":547,"passed_time":2.749965781,"remaining_time":2.268219951},
{"learn":[0.1721931044],"iteration":548,"passed_time":2.753273119,"remaining_time":2.261796314},
{"learn":[0.1720683086],"iteration":549,"passed_time":2.757560267,"remaining_time":2.256185673},
{"learn":[0.1719568752],"iteration":550,"passed_time":2.760676896,"remaining_time":2.249626},
{"learn":[0.1717076891],"iteration":551,"passed_time":2.76403963,"remaining_time":2.24327854},
{"learn":[0.1714463793],"iteration":552,"passed_time":2.767470311,"remaining_time":2.236996798},
{"learn":[0.1712525035],"iteration":553,"passed_time":2.770993079,"remaining_time":2.230799482},
{"learn":[0.1711476847],"iteration":554,"passed_time":2.77429065,"remaining_time":2.224431242},
{"learn":[0.1710143475],"iteration":555,"passed_time":2.777503666,"remaining_time":2.218006524},
{"learn":[0.1708647248],"iteration":556,"passed_time":2.780534653,"remaining_time":2.211448566},
{"learn":[0.1707092914],"iteration":557,"passed_time":2.783827674,"remaining_time":2.20511081},
{"learn":[0.1705809332],"iteration":558,"passed_time":2.787182937,"remaining_time":2.19883305},
{"learn":[0.1703515794],"iteration":559,"passed_time":2.790526511,"remaining_time":2.192556544},
{"learn":[0.1702054613],"iteration":560,"passed_time":2.793866646,"remaining_time":2.186287803},
{"learn":[0.1699672339],"iteration":561,"passed_time":2.797284189,"remaining_time":2.180089813},
{"learn":[0.1696505159],"iteration":562,"passed_time":2.800780581,"remaining_time":2.173962902},
{"learn":[0.1695089245],"iteration":563,"passed_time":2.804329068,"remaining_time":2.167885591},
{"learn":[0.169374062],"iteration":564,"passed_time":2.807651209,"remaining_time":2.161642966},
{"learn":[0.1691004809],"iteration":565,"passed_time":2.81122561,"remaining_time":2.15560409},
{"learn":[0.1688769236],"iteration":566,"passed_time":2.814637129,"remaining_time":2.149449518},
{"learn":[0.1687051529],"iteration":567,"passed_time":2.818389191,"remaining_time":2.14356361},
{"learn":[0.1684595113],"iteration":568,"passed_time":2.822079534,"remaining_time":2.137638452},
{"learn":[0.1681710925],"iteration":569,"passed_time":2.825679698,"remaining_time":2.131653106},
{"learn":[0.1680404031],"iteration":570,"passed_time":2.829086268,"remaining_time":2.125530664},
{"learn":[0.1679430984],"iteration":571,"passed_time":2.833374151,"remaining_time":2.120077162},
{"learn":[0.1678433846],"iteration":572,"passed_time":2.837495951,"remaining_time":2.114503964},
{"learn":[0.1677256939],"iteration":573,"passed_time":2.841046535,"remaining_time":2.108511889},
{"learn":[0.1674646332],"iteration":574,"passed_time":2.844825242,"remaining_time":2.102696918},
{"learn":[0.1672593325],"iteration":575,"passed_time":2.848365108,"remaining_time":2.096713204},
{"learn":[0.1671332006],"iteration":576,"passed_time":2.852486132,"remaining_time":2.09116401},
{"learn":[0.1670278871],"iteration":577,"passed_time":2.856179971,"remaining_time":2.085307868},
{"learn":[0.1669028422],"iteration":578,"passed_time":2.859660119,"remaining_time":2.079303817},
{"learn":[0.166768419],"iteration":579,"passed_time":2.863200581,"remaining_time":2.073352145},
{"learn":[0.1664641992],"iteration":580,"passed_time":2.866826429,"remaining_time":2.06747035},
{"learn":[0.1662374329],"iteration":581,"passed_time":2.870421297,"remaining_time":2.061574059},
{"learn":[0.1660463648],"iteration":582,"passed_time":2.87409369,"remaining_time":2.055741113},
{"learn":[0.1656560149],"iteration":583,"passed_time":2.87791661,"remaining_time":2.050022791},
{"learn":[0.1654407104],"iteration":584,"passed_time":2.881324091,"remaining_time":2.044016236},
{"learn":[0.165283492],"iteration":585,"passed_time":2.88481837,"remaining_time":2.038079872},
{"learn":[0.1651754062],"iteration":586,"passed_time":2.888134915,"remaining_time":2.03202678},
{"learn":[0.1650618337],"iteration":587,"passed_time":2.891919711,"remaining_time":2.02631109},
{"learn":[0.1649050958],"iteration":588,"passed_time":2.895371111,"remaining_time":2.020369315},
{"learn":[0.1647921643],"iteration":589,"passed_time":2.898891669,"remaining_time":2.014484041},
{"learn":[0.1645804841],"iteration":590,"passed_time":2.90215444,"remaining_time":2.008428369},
{"learn":[0.1643798491],"iteration":591,"passed_time":2.905405005,"remaining_time":2.00237372},
{"learn":[0.164261908],"iteration":592,"passed_time":2.908656433,"remaining_time":1.99632912},
{"learn":[0.1640290878],"iteration":593,"passed_time":2.912004079,"remaining_time":1.99035969},
{"learn":[0.1637102452],"iteration":594,"passed_time":2.915268067,"remaining_time":1.984342129},
{"learn":[0.1636023806],"iteration":595,"passed_time":2.918692409,"remaining_time":1.978442506},
{"learn":[0.1635030058],"iteration":596,"passed_time":2.92188857,"remaining_time":1.972397142},
{"learn":[0.1633222594],"iteration":597,"passed_time":2.925190513,"remaining_time":1.966432419},
{"learn":[0.1631007446],"iteration":598,"passed_time":2.928235341,"remaining_time":1.960304461},
{"learn":[0.1628718718],"iteration":599,"passed_time":2.931523793,"remaining_time":1.954349195},
{"learn":[0.1627783669],"iteration":600,"passed_time":2.934605971,"remaining_time":1.948265861},
{"learn":[0.1626563755],"iteration":601,"passed_time":2.937714315,"remaining_time":1.942209796},
{"learn":[0.1625286717],"iteration":602,"passed_time":2.941428259,"remaining_time":1.93656222},
{"learn":[0.1623270545],"iteration":603,"passed_time":2.945157377,"remaining_time":1.930930996},
{"learn":[0.162238085],"iteration":604,"passed_time":2.948471412,"remaining_time":1.925035054},
{"learn":[0.1620838609],"iteration":605,"passed_time":2.951860808,"remaining_time":1.919196631},
{"learn":[0.1617748142],"iteration":606,"passed_time":2.955145541,"remaining_time":1.913298514},
{"learn":[0.1615209597],"iteration":607,"passed_time":2.958550875,"remaining_time":1.907486749},
{"learn":[0.1614202412],"iteration":608,"passed_time":2.961712854,"remaining_time":1.901526644},
{"learn":[0.1613047168],"iteration":609,"passed_time":2.964854403,"remaining_time":1.895562651},
{"learn":[0.1612201891],"iteration":610,"passed_time":2.968419551,"remaining_time":1.889877586},
{"learn":[0.1610759895],"iteration":611,"passed_time":2.971824998,"remaining_time":1.884098202},
{"learn":[0.1609188119],"iteration":612,"passed_time":2.974957446,"remaining_time":1.878154211},
{"learn":[0.1608280487],"iteration":613,"passed_time":2.978559064,"remaining_time":1.87251433},
{"learn":[0.1607378506],"iteration":614,"passed_time":2.981758324,"remaining_time":1.866629195},
{"learn":[0.1602788839],"iteration":615,"passed_time":2.985267523,"remaining_time":1.860945988},
{"learn":[0.160103767],"iteration":616,"passed_time":2.988638555,"remaining_time":1.855184062},
{"learn":[0.159899943],"iteration":617,"passed_time":2.991822322,"remaining_time":1.849314121},
{"learn":[0.1596575998],"iteration":618,"passed_time":2.994942036,"remaining_time":1.843413434},
{"learn":[0.1594769688],"iteration":619,"passed_time":2.998112303,"remaining_time":1.837552702},
{"learn":[0.1593674749],"iteration":620,"passed_time":3.001440077,"remaining_time":1.831796762},
{"learn":[0.1591022699],"iteration":621,"passed_time":3.004697913,"remaining_time":1.826006127},
{"learn":[0.1588639754],"iteration":622,"passed_time":3.007988747,"remaining_time":1.820243592},
{"learn":[0.1586540115],"iteration":623,"passed_time":3.011154231,"remaining_time":1.814413447},
{"learn":[0.1584549961],"iteration":624,"passed_time":3.014350859,"remaining_time":1.808610515},
{"learn":[0.1583332447],"iteration":625,"passed_time":3.0176163,"remaining_time":1.802857023},
{"learn":[0.1582412854],"iteration":626,"passed_time":3.021029513,"remaining_time":1.797199375},
{"learn":[0.157966575],"iteration":627,"passed_time":3.024319345,"remaining_time":1.791475791},
{"learn":[0.1578425423],"iteration":628,"passed_time":3.028330687,"remaining_time":1.786185509},
{"learn":[0.1577326082],"iteration":629,"passed_time":3.031791472,"remaining_time":1.780575944},
{"learn":[0.1575671094],"iteration":630,"passed_time":3.036711701,"remaining_time":1.775826652},
{"learn":[0.1574937853],"iteration":631,"passed_time":3.040406845,"remaining_time":1.77036348},
{"learn":[0.1573970718],"iteration":632,"passed_time":3.045122991,"remaining_time":1.765497848},
{"learn":[0.1572985456],"iteration":633,"passed_time":3.049367563,"remaining_time":1.760360454},
{"learn":[0.1571266139],"iteration":634,"passed_time":3.054200578,"remaining_time":1.755564112},
{"learn":[0.1569603138],"iteration":635,"passed_time":3.058221264,"remaining_time":1.750302736},
{"learn":[0.1568652272],"iteration":636,"passed_time":3.064088434,"remaining_time":1.746097491},
{"learn":[0.1567085566],"iteration":637,"passed_time":3.070269546,"remaining_time":1.742065165},
{"learn":[0.1565418492],"iteration":638,"passed_time":3.075403958,"remaining_time":1.737434787},
{"learn":[0.1564318631],"iteration":639,"passed_time":3.079389299,"remaining_time":1.73215648},
{"learn":[0.156265501],"iteration":640,"passed_time":3.084104743,"remaining_time":1.727291112},
{"learn":[0.155900537],"iteration":641,"passed_time":3.088825627,"remaining_time":1.722429244},
{"learn":[0.1556825417],"iteration":642,"passed_time":3.092767543,"remaining_time":1.717135324},
{"learn":[0.1556123642],"iteration":643,"passed_time":3.097737038,"remaining_time":1.712413642},
{"learn":[0.1552878528],"iteration":644,"passed_time":3.103161925,"remaining_time":1.707941835},
{"learn":[0.1551803207],"iteration":645,"passed_time":3.107786003,"remaining_time":1.703028243},
{"learn":[0.1550432423],"iteration":646,"passed_time":3.112334779,"remaining_time":1.698074462},
{"learn":[0.1548720874],"iteration":647,"passed_time":3.117766477,"remaining_time":1.693601543},
{"learn":[0.1547510672],"iteration":648,"passed_time":3.122997701,"remaining_time":1.689017247},
{"learn":[0.1545460714],"iteration":649,"passed_time":3.128077706,"remaining_time":1.684349534},
{"learn":[0.1544494252],"iteration":650,"passed_time":3.132845788,"remaining_time":1.679513333},
{"learn":[0.1542929968],"iteration":651,"passed_time":3.136611935,"remaining_time":1.674142566},
{"learn":[0.1541266954],"iteration":652,"passed_time":3.141010404,"remaining_time":1.669112726},
{"learn":[0.1539680819],"iteration":653,"passed_time":3.144157523,"remaining_time":1.663422787},
{"learn":[0.153813614],"iteration":654,"passed_time":3.149302724,"remaining_time":1.658793038},
{"learn":[0.1537077729],"iteration":655,"passed_time":3.1533459,"remaining_time":1.653583826},
{"learn":[0.1534084005],"iteration":656,"passed_time":3.16124178,"remaining_time":1.650389544},
{"learn":[0.1532977226],"iteration":657,"passed_time":3.167139104,"remaining_time":1.646142209},
{"learn":[0.1530837725],"iteration":658,"passed_time":3.171495372,"remaining_time":1.641092446},
{"learn":[0.152989027],"iteration":659,"passed_time":3.177669799,"remaining_time":1.636981411},
{"learn":[0.1528490836],"iteration":660,"passed_time":3.184160244,"remaining_time":1.633026207},
{"learn":[0.1526833154],"iteration":661,"passed_time":3.189571545,"remaining_time":1.62851236},
{"learn":[0.1526074679],"iteration":662,"passed_time":3.19471927,"remaining_time":1.623861831},
{"learn":[0.1524291849],"iteration":663,"passed_time":3.198558245,"remaining_time":1.618547546},
{"learn":[0.1523396266],"iteration":664,"passed_time":3.203640299,"remaining_time":1.61386391},
{"learn":[0.1522011278],"iteration":665,"passed_time":3.20908473,"remaining_time":1.60936081},
{"learn":[0.1520684161],"iteration":666,"passed_time":3.213831929,"remaining_time":1.604506795},
{"learn":[0.1519891857],"iteration":667,"passed_time":3.217967737,"remaining_time":1.599349235},
{"learn":[0.1519298261],"iteration":668,"passed_time":3.223424027,"remaining_time":1.594848061},
{"learn":[0.1518371456],"iteration":669,"passed_time":3.230936379,"remaining_time":1.591356724},
{"learn":[0.1515956094],"iteration":670,"passed_time":3.23596188,"remaining_time":1.586634066},
{"learn":[0.1514716001],"iteration":671,"passed_time":3.239834244,"remaining_time":1.581347667},
{"learn":[0.1513300282],"iteration":672,"passed_time":3.24371817,"remaining_time":1.576071087},
{"learn":[0.1512342445],"iteration":673,"passed_time":3.247602392,"remaining_time":1.570798783},
{"learn":[0.1510366455],"iteration":674,"passed_time":3.25100517,"remaining_time":1.565298786},
{"learn":[0.1509774794],"iteration":675,"passed_time":3.254740543,"remaining_time":1.559964402},
{"learn":[0.150851276],"iteration":676,"passed_time":3.258231161,"remaining_time":1.554517969},
{"learn":[0.1506550052],"iteration":677,"passed_time":3.262422825,"remaining_time":1.54941025},
{"learn":[0.150456011],"iteration":678,"passed_time":3.266557254,"remaining_time":1.544278172},
{"learn":[0.1503336381],"iteration":679,"passed_time":3.270471498,"remaining_time":1.539045411},
{"learn":[0.1501482135],"iteration":680,"passed_time":3.274302213,"remaining_time":1.533777395},
{"learn":[0.1499040108],"iteration":681,"passed_time":3.27780016,"remaining_time":1.528358432},
{"learn":[0.1497262598],"iteration":682,"passed_time":3.281649041,"remaining_time":1.523107974},
{"learn":[0.1496009278],"iteration":683,"passed_time":3.284832303,"remaining_time":1.517554105},
{"learn":[0.1495121032],"iteration":684,"passed_time":3.288433663,"remaining_time":1.512199422},
{"learn":[0.1493749726],"iteration":685,"passed_time":3.291644906,"remaining_time":1.506671284},
{"learn":[0.1491563732],"iteration":686,"passed_time":3.294921256,"remaining_time":1.501179553},
{"learn":[0.1490296665],"iteration":687,"passed_time":3.298059519,"remaining_time":1.495631642},
{"learn":[0.148859926],"iteration":688,"passed_time":3.301214112,"remaining_time":1.490098097},
{"learn":[0.1486859422],"iteration":689,"passed_time":3.304366921,"remaining_time":1.484570645},
{"learn":[0.1484348696],"iteration":690,"passed_time":3.307690535,"remaining_time":1.479126448},
{"learn":[0.1483648188],"iteration":691,"passed_time":3.310992962,"remaining_time":1.473678948},
{"learn":[0.1482185303],"iteration":692,"passed_time":3.314369149,"remaining_time":1.468270316},
{"learn":[0.1481059692],"iteration":693,"passed_time":3.317508834,"remaining_time":1.462763261},
{"learn":[0.1480277763],"iteration":694,"passed_time":3.320733812,"remaining_time":1.45730045},
{"learn":[0.1479123014],"iteration":695,"passed_time":3.324026309,"remaining_time":1.45187356},
{"learn":[0.1477637377],"iteration":696,"passed_time":3.327450914,"remaining_time":1.446510225},
{"learn":[0.1475286421],"iteration":697,"passed_time":3.330571134,"remaining_time":1.441020748},
{"learn":[0.1473566157],"iteration":698,"passed_time":3.334283605,"remaining_time":1.435793083},
{"learn":[0.1472260221],"iteration":699,"passed_time":3.337574472,"remaining_time":1.43038906},
{"learn":[0.1471565983],"iteration":700,"passed_time":3.340897823,"remaining_time":1.42500492},
{"learn":[0.1470788035],"iteration":701,"passed_time":3.344187493,"remaining_time":1.419612355},
{"learn":[0.1469008019],"iteration":702,"passed_time":3.347537027,"remaining_time":1.414251063},
{"learn":[0.1467298328],"iteration":703,"passed_time":3.350851043,"remaining_time":1.408880552},
{"learn":[0.1465309725],"iteration":704,"passed_time":3.354403506,"remaining_time":1.403615652},
{"learn":[0.1464281448],"iteration":705,"passed_time":3.357735838,"remaining_time":1.398263933},
{"learn":[0.1462469623],"iteration":706,"passed_time":3.360923534,"remaining_time":1.392857985},
{"learn":[0.1460982373],"iteration":707,"passed_time":3.364210209,"remaining_time":1.387499126},
{"learn":[0.145910644],"iteration":708,"passed_time":3.367280188,"remaining_time":1.382057172},
{"learn":[0.1457397853],"iteration":709,"passed_time":3.370390372,"remaining_time":1.376638321},
{"learn":[0.1456368896],"iteration":710,"passed_time":3.373791274,"remaining_time":1.371344132},
{"learn":[0.1455391126],"iteration":711,"passed_time":3.377103893,"remaining_time":1.366019552},
{"learn":[0.1452691618],"iteration":712,"passed_time":3.38027959,"remaining_time":1.360645501},
{"learn":[0.145179468],"iteration":713,"passed_time":3.38372034,"remaining_time":1.355383778},
{"learn":[0.1448754721],"iteration":714,"passed_time":3.386859192,"remaining_time":1.350006811},
{"learn":[0.144697944],"iteration":715,"passed_time":3.39027828,"remaining_time":1.344747251},
{"learn":[0.144294597],"iteration":716,"passed_time":3.393713087,"remaining_time":1.339499029},
{"learn":[0.1440696037],"iteration":717,"passed_time":3.397021638,"remaining_time":1.33420627},
{"learn":[0.1438178436],"iteration":718,"passed_time":3.400265475,"remaining_time":1.328893739},
{"learn":[0.143621903],"iteration":719,"passed_time":3.403951346,"remaining_time":1.323758857},
{"learn":[0.1432744117],"iteration":720,"passed_time":3.407200827,"remaining_time":1.318459127},
{"learn":[0.1430755798],"iteration":721,"passed_time":3.410556438,"remaining_time":1.313205942},
{"learn":[0.1429183476],"iteration":722,"passed_time":3.414460561,"remaining_time":1.308168154},
{"learn":[0.1427765253],"iteration":723,"passed_time":3.41768283,"remaining_time":1.302873565},
{"learn":[0.1425712469],"iteration":724,"passed_time":3.420945006,"remaining_time":1.29759983},
{"learn":[0.1423050273],"iteration":725,"passed_time":3.42437987,"remaining_time":1.29239681},
{"learn":[0.142150875],"iteration":726,"passed_time":3.427407528,"remaining_time":1.287045743},
{"learn":[0.1419907821],"iteration":727,"passed_time":3.431055375,"remaining_time":1.281932778},
{"learn":[0.1418947721],"iteration":728,"passed_time":3.435137573,"remaining_time":1.276985298},
{"learn":[0.1417077843],"iteration":729,"passed_time":3.438820404,"remaining_time":1.271892478},
{"learn":[0.1416227712],"iteration":730,"passed_time":3.442667007,"remaining_time":1.266863782},
{"learn":[0.1414821754],"iteration":731,"passed_time":3.445803245,"remaining_time":1.261578237},
{"learn":[0.1414080932],"iteration":732,"passed_time":3.449780672,"remaining_time":1.256604965},
{"learn":[0.1412027469],"iteration":733,"passed_time":3.453036917,"remaining_time":1.251373052},
{"learn":[0.1409251965],"iteration":734,"passed_time":3.456298478,"remaining_time":1.246148431},
{"learn":[0.1408268781],"iteration":735,"passed_time":3.459485807,"remaining_time":1.240902518},
{"learn":[0.1405937396],"iteration":736,"passed_time":3.462769976,"remaining_time":1.235696749},
{"learn":[0.140527981],"iteration":737,"passed_time":3.466053477,"remaining_time":1.23049595},
{"learn":[0.1402156962],"iteration":738,"passed_time":3.469212461,"remaining_time":1.225256363},
{"learn":[0.1401330763],"iteration":739,"passed_time":3.472627135,"remaining_time":1.220112236},
{"learn":[0.1400320252],"iteration":740,"passed_time":3.476312289,"remaining_time":1.215067318},
{"learn":[0.1398436728],"iteration":741,"passed_time":3.47937767,"remaining_time":1.209810565},
{"learn":[0.1395921995],"iteration":742,"passed_time":3.482553988,"remaining_time":1.204598082},
{"learn":[0.1394109363],"iteration":743,"passed_time":3.485671302,"remaining_time":1.199370771},
{"learn":[0.139311902],"iteration":744,"passed_time":3.488695778,"remaining_time":1.194117347},
{"learn":[0.1392266789],"iteration":745,"passed_time":3.492002096,"remaining_time":1.188965861},
{"learn":[0.1391006578],"iteration":746,"passed_time":3.495123382,"remaining_time":1.183756648},
{"learn":[0.1389589305],"iteration":747,"passed_time":3.498409782,"remaining_time":1.178608643},
{"learn":[0.1388027146],"iteration":748,"passed_time":3.501635226,"remaining_time":1.173445183},
{"learn":[0.1387226683],"iteration":749,"passed_time":3.504786485,"remaining_time":1.168262162},
{"learn":[0.1382747053],"iteration":750,"passed_time":3.508108819,"remaining_time":1.163141273},
{"learn":[0.1379869415],"iteration":751,"passed_time":3.51142107,"remaining_time":1.158021842},
{"learn":[0.1377909765],"iteration":752,"passed_time":3.514552011,"remaining_time":1.152847738},
{"learn":[0.1376055587],"iteration":753,"passed_time":3.51777534,"remaining_time":1.147709196},
{"learn":[0.1373873849],"iteration":754,"passed_time":3.521183967,"remaining_time":1.142635857},
{"learn":[0.1372114408],"iteration":755,"passed_time":3.52471784,"remaining_time":1.137607345},
{"learn":[0.1370590532],"iteration":756,"passed_time":3.52784354,"remaining_time":1.132451757},
{"learn":[0.1369587298],"iteration":757,"passed_time":3.531152778,"remaining_time":1.127360122},
{"learn":[0.1368620523],"iteration":758,"passed_time":3.534719181,"remaining_time":1.122354839},
{"learn":[0.1364844617],"iteration":759,"passed_time":3.538205523,"remaining_time":1.11732806},
{"learn":[0.1363949844],"iteration":760,"passed_time":3.541848902,"remaining_time":1.112354649},
{"learn":[0.1362857845],"iteration":761,"passed_time":3.545360704,"remaining_time":1.107343632},
{"learn":[0.1360455421],"iteration":762,"passed_time":3.548866895,"remaining_time":1.102334802},
{"learn":[0.1358923025],"iteration":763,"passed_time":3.552755339,"remaining_time":1.097447984},
{"learn":[0.1358375599],"iteration":764,"passed_time":3.556176334,"remaining_time":1.092420181},
{"learn":[0.1357647564],"iteration":765,"passed_time":3.559840568,"remaining_time":1.087470879},
{"learn":[0.13559373],"iteration":766,"passed_time":3.563148647,"remaining_time":1.082416734},
{"learn":[0.1354590215],"iteration":767,"passed_time":3.566572711,"remaining_time":1.077402173},
{"learn":[0.1352790906],"iteration":768,"passed_time":3.570000439,"remaining_time":1.07239285},
{"learn":[0.1352060213],"iteration":769,"passed_time":3.573592839,"remaining_time":1.067436822},
{"learn":[0.1349566706],"iteration":770,"passed_time":3.577029296,"remaining_time":1.062438014},
{"learn":[0.1348674562],"iteration":771,"passed_time":3.580586189,"remaining_time":1.057478823},
{"learn":[0.1347229783],"iteration":772,"passed_time":3.583951448,"remaining_time":1.052466984},
{"learn":[0.1346190176],"iteration":773,"passed_time":3.588229624,"remaining_time":1.047725962},
{"learn":[0.1344938238],"iteration":774,"passed_time":3.59198556,"remaining_time":1.042834517},
{"learn":[0.1344326589],"iteration":775,"passed_time":3.595331483,"remaining_time":1.037827645},
{"learn":[0.1343111446],"iteration":776,"passed_time":3.599356991,"remaining_time":1.033020089},
{"learn":[0.1342025456],"iteration":777,"passed_time":3.602723828,"remaining_time":1.028026594},
{"learn":[0.1340281445],"iteration":778,"passed_time":3.606214786,"remaining_time":1.023072487},
{"learn":[0.133958763],"iteration":779,"passed_time":3.610212815,"remaining_time":1.018265153},
{"learn":[0.1338686025],"iteration":780,"passed_time":3.613974498,"remaining_time":1.013393617},
{"learn":[0.1337809183],"iteration":781,"passed_time":3.617465378,"remaining_time":1.008449427},
{"learn":[0.1336075033],"iteration":782,"passed_time":3.621048968,"remaining_time":1.003534644},
{"learn":[0.1334979611],"iteration":783,"passed_time":3.624373371,"remaining_time":0.9985518471},
{"learn":[0.1333425684],"iteration":784,"passed_time":3.62819799,"remaining_time":0.9937102774},
{"learn":[0.133182746],"iteration":785,"passed_time":3.631750053,"remaining_time":0.9887970883},
{"learn":[0.1331257666],"iteration":786,"passed_time":3.635290949,"remaining_time":0.9838843355},
{"learn":[0.132882104],"iteration":787,"passed_time":3.638841111,"remaining_time":0.9789775579},
{"learn":[0.1328214954],"iteration":788,"passed_time":3.642311213,"remaining_time":0.9740528086},
{"learn":[0.1326569298],"iteration":789,"passed_time":3.646397386,"remaining_time":0.9692955076},
{"learn":[0.1325321512],"iteration":790,"passed_time":3.649824619,"remaining_time":0.964365797},
{"learn":[0.1324375628],"iteration":791,"passed_time":3.653289219,"remaining_time":0.9594496938},
{"learn":[0.1321014247],"iteration":792,"passed_time":3.656873915,"remaining_time":0.9545686007},
{"learn":[0.1318341079],"iteration":793,"passed_time":3.660694359,"remaining_time":0.949751937},
{"learn":[0.1316919289],"iteration":794,"passed_time":3.664140268,"remaining_time":0.9448412013},
{"learn":[0.1316502692],"iteration":795,"passed_time":3.667697015,"remaining_time":0.9399625515},
{"learn":[0.1314592398],"iteration":796,"passed_time":3.671070825,"remaining_time":0.9350406243},
{"learn":[0.1312222531],"iteration":797,"passed_time":3.674764029,"remaining_time":0.930203426},
{"learn":[0.1310277724],"iteration":798,"passed_time":3.679103379,"remaining_time":0.9255316385},
{"learn":[0.1308412549],"iteration":799,"passed_time":3.682956937,"remaining_time":0.9207392343},
{"learn":[0.1306574684],"iteration":800,"passed_time":3.686521193,"remaining_time":0.9158773002},
{"learn":[0.1304996651],"iteration":801,"passed_time":3.690112404,"remaining_time":0.9110252568},
{"learn":[0.130401876],"iteration":802,"passed_time":3.693610496,"remaining_time":0.9061535091},
{"learn":[0.1302518861],"iteration":803,"passed_time":3.697160985,"remaining_time":0.9012979517},
{"learn":[0.1301636897],"iteration":804,"passed_time":3.700831297,"remaining_time":0.8964746621},
{"learn":[0.130106487],"iteration":805,"passed_time":3.704091508,"remaining_time":0.8915555243},
{"learn":[0.1300158474],"iteration":806,"passed_time":3.707617005,"remaining_time":0.886703943},
{"learn":[0.1299589011],"iteration":807,"passed_time":3.710950151,"remaining_time":0.8818099369},
{"learn":[0.129919445],"iteration":808,"passed_time":3.714806771,"remaining_time":0.8770433787},
{"learn":[0.1297219653],"iteration":809,"passed_time":3.71842169,"remaining_time":0.8722223717},
{"learn":[0.1296219918],"iteration":810,"passed_time":3.722151198,"remaining_time":0.8674310438},
{"learn":[0.1294727653],"iteration":811,"passed_time":3.725616563,"remaining_time":0.8625811747},
{"learn":[0.1293203525],"iteration":812,"passed_time":3.729211327,"remaining_time":0.8577644749},
{"learn":[0.1290958235],"iteration":813,"passed_time":3.732764307,"remaining_time":0.8529412299},
{"learn":[0.1289673174],"iteration":814,"passed_time":3.736636676,"remaining_time":0.8481936013},
{"learn":[0.1287675286],"iteration":815,"passed_time":3.740461723,"remaining_time":0.8434374475},
{"learn":[0.1285688307],"iteration":816,"passed_time":3.744156391,"remaining_time":0.8386543691},
{"learn":[0.12844905],"iteration":817,"passed_time":3.747872435,"remaining_time":0.833878708},
{"learn":[0.128274841],"iteration":818,"passed_time":3.751468276,"remaining_time":0.8290790696},
{"learn":[0.1281401264],"iteration":819,"passed_time":3.755191365,"remaining_time":0.8243102996},
{"learn":[0.1279905426],"iteration":820,"passed_time":3.758691708,"remaining_time":0.8194955124},
{"learn":[0.1277753456],"iteration":821,"passed_time":3.763085057,"remaining_time":0.8148772994},
{"learn":[0.1276654417],"iteration":822,"passed_time":3.7690428,"remaining_time":0.8105960821},
{"learn":[0.1274833042],"iteration":823,"passed_time":3.775051273,"remaining_time":0.8063216312},
{"learn":[0.1274309027],"iteration":824,"passed_time":3.778469583,"remaining_time":0.8014935479},
{"learn":[0.1272849099],"iteration":825,"passed_time":3.783053486,"remaining_time":0.7969144147},
{"learn":[0.1271943732],"iteration":826,"passed_time":3.786848188,"remaining_time":0.7921701772},
{"learn":[0.1270745285],"iteration":827,"passed_time":3.790404398,"remaining_time":0.7873786913},
{"learn":[0.1269067306],"iteration":828,"passed_time":3.793955676,"remaining_time":0.7825891684},
{"learn":[0.1267494034],"iteration":829,"passed_time":3.797402885,"remaining_time":0.7777813137},
{"learn":[0.1267044172],"iteration":830,"passed_time":3.800760245,"remaining_time":0.7729584614},
{"learn":[0.1265647366],"iteration":831,"passed_time":3.804079878,"remaining_time":0.7681315137},
{"learn":[0.1264949242],"iteration":832,"passed_time":3.807896053,"remaining_time":0.763407732},
{"learn":[0.1263458029],"iteration":833,"passed_time":3.811242507,"remaining_time":0.7585926333},
{"learn":[0.1261758196],"iteration":834,"passed_time":3.814645219,"remaining_time":0.7537921691},
{"learn":[0.1260713319],"iteration":835,"passed_time":3.818124102,"remaining_time":0.7490099913},
{"learn":[0.1259836376],"iteration":836,"passed_time":3.821780091,"remaining_time":0.744265418},
{"learn":[0.1258333865],"iteration":837,"passed_time":3.825305222,"remaining_time":0.7394981455},
{"learn":[0.1257599071],"iteration":838,"passed_time":3.829249529,"remaining_time":0.7348142719},
{"learn":[0.1255584502],"iteration":839,"passed_time":3.832823016,"remaining_time":0.7300615268},
{"learn":[0.1254588761],"iteration":840,"passed_time":3.837070944,"remaining_time":0.7254390965},
{"learn":[0.1253223522],"iteration":841,"passed_time":3.841602793,"remaining_time":0.7208708329},
{"learn":[0.1252257889],"iteration":842,"passed_time":3.845537917,"remaining_time":0.716191522},
{"learn":[0.1251404822],"iteration":843,"passed_time":3.849320724,"remaining_time":0.711485821},
{"learn":[0.1249870086],"iteration":844,"passed_time":3.853076673,"remaining_time":0.7067773779},
{"learn":[0.1248468912],"iteration":845,"passed_time":3.856697739,"remaining_time":0.7020466334},
{"learn":[0.1247451091],"iteration":846,"passed_time":3.860282027,"remaining_time":0.6973118655},
{"learn":[0.1246742328],"iteration":847,"passed_time":3.863871182,"remaining_time":0.6925806836},
{"learn":[0.1245747892],"iteration":848,"passed_time":3.867297334,"remaining_time":0.6878232008},
{"learn":[0.124527736],"iteration":849,"passed_time":3.871295376,"remaining_time":0.6831697723},
{"learn":[0.1243986532],"iteration":850,"passed_time":3.875366414,"remaining_time":0.6785306647},
{"learn":[0.1242075073],"iteration":851,"passed_time":3.87912561,"remaining_time":0.673838721},
{"learn":[0.1240941016],"iteration":852,"passed_time":3.882979677,"remaining_time":0.6691653137},
{"learn":[0.1240136032],"iteration":853,"passed_time":3.886611999,"remaining_time":0.6644559155},
{"learn":[0.1239092631],"iteration":854,"passed_time":3.890353989,"remaining_time":0.6597676355},
{"learn":[0.1237055758],"iteration":855,"passed_time":3.89370666,"remaining_time":0.6550160736},
{"learn":[0.1235735171],"iteration":856,"passed_time":3.897195968,"remaining_time":0.6502905757},
{"learn":[0.1234354527],"iteration":857,"passed_time":3.900565497,"remaining_time":0.6455481358},
{"learn":[0.1233146241],"iteration":858,"passed_time":3.904131948,"remaining_time":0.6408412162},
{"learn":[0.1232230232],"iteration":859,"passed_time":3.907456532,"remaining_time":0.6360975749},
{"learn":[0.1231653551],"iteration":860,"passed_time":3.910735104,"remaining_time":0.6313498019},
{"learn":[0.1230351368],"iteration":861,"passed_time":3.913968865,"remaining_time":0.6265982638},
{"learn":[0.1229052749],"iteration":862,"passed_time":3.917265387,"remaining_time":0.6218602062},
{"learn":[0.1228163515],"iteration":863,"passed_time":3.920544053,"remaining_time":0.6171226749},
{"learn":[0.1227085054],"iteration":864,"passed_time":3.924370598,"remaining_time":0.6124740239},
{"learn":[0.1226673067],"iteration":865,"passed_time":3.928372323,"remaining_time":0.6078543779},
{"learn":[0.122544305],"iteration":866,"passed_time":3.931983904,"remaining_time":0.6031763083},
{"learn":[0.1223927901],"iteration":867,"passed_time":3.935249163,"remaining_time":0.5984480294},
{"learn":[0.1223353293],"iteration":868,"passed_time":3.938696256,"remaining_time":0.5937505288},
{"learn":[0.122214109],"iteration":869,"passed_time":3.942035333,"remaining_time":0.5890397624},
{"learn":[0.1220944495],"iteration":870,"passed_time":3.946036926,"remaining_time":0.5844302681},
{"learn":[0.1219333331],"iteration":871,"passed_time":3.949856619,"remaining_time":0.5797954669},
{"learn":[0.1218386522],"iteration":872,"passed_time":3.953671732,"remaining_time":0.5751618671},
{"learn":[0.1216670602],"iteration":873,"passed_time":3.957088277,"remaining_time":0.5704726807},
{"learn":[0.1215239836],"iteration":874,"passed_time":3.960392176,"remaining_time":0.5657703109},
{"learn":[0.1214370355],"iteration":875,"passed_time":3.964615905,"remaining_time":0.5612013381},
{"learn":[0.1213730604],"iteration":876,"passed_time":3.968286858,"remaining_time":0.5565556254},
{"learn":[0.1213076596],"iteration":877,"passed_time":3.97227191,"remaining_time":0.5519557779},
{"learn":[0.1212359019],"iteration":878,"passed_time":3.975786953,"remaining_time":0.5472926295},
{"learn":[0.1211200621],"iteration":879,"passed_time":3.979346764,"remaining_time":0.542638195},
{"learn":[0.1210344984],"iteration":880,"passed_time":3.98304974,"remaining_time":0.5380055835},
{"learn":[0.1208567114],"iteration":881,"passed_time":3.987289494,"remaining_time":0.5334468937},
{"learn":[0.1207913066],"iteration":882,"passed_time":3.991075319,"remaining_time":0.5288287795},
{"learn":[0.1207126676],"iteration":883,"passed_time":3.994954447,"remaining_time":0.5242247917},
{"learn":[0.1206566821],"iteration":884,"passed_time":3.999284802,"remaining_time":0.5196810759},
{"learn":[0.1205074701],"iteration":885,"passed_time":4.004349442,"remaining_time":0.515232321},
{"learn":[0.1204361307],"iteration":886,"passed_time":4.010276461,"remaining_time":0.5108920407},
{"learn":[0.120329962],"iteration":887,"passed_time":4.014067795,"remaining_time":0.506278821},
{"learn":[0.1202149281],"iteration":888,"passed_time":4.018063527,"remaining_time":0.5016929714},
{"learn":[0.1200789166],"iteration":889,"passed_time":4.022215414,"remaining_time":0.4971277479},
{"learn":[0.1199483922],"iteration":890,"passed_time":4.02687832,"remaining_time":0.4926259674},
{"learn":[0.119843168],"iteration":891,"passed_time":4.031249309,"remaining_time":0.4880884814},
{"learn":[0.1197092451],"iteration":892,"passed_time":4.035816785,"remaining_time":0.4835749116},
{"learn":[0.1196493488],"iteration":893,"passed_time":4.039700384,"remaining_time":0.4789801351},
{"learn":[0.1195798492],"iteration":894,"passed_time":4.042885133,"remaining_time":0.4743049597},
{"learn":[0.1195035035],"iteration":895,"passed_time":4.046612539,"remaining_time":0.4696960982},
{"learn":[0.1194540844],"iteration":896,"passed_time":4.049906502,"remaining_time":0.4650394311},
{"learn":[0.1193285266],"iteration":897,"passed_time":4.054984207,"remaining_time":0.4605884066},
{"learn":[0.1191916521],"iteration":898,"passed_time":4.058501241,"remaining_time":0.4559606511},
{"learn":[0.1190581496],"iteration":899,"passed_time":4.061942928,"remaining_time":0.451326992},
{"learn":[0.1189971347],"iteration":900,"passed_time":4.065513713,"remaining_time":0.4467101638},
{"learn":[0.1188959984],"iteration":901,"passed_time":4.068837359,"remaining_time":0.4420688039},
{"learn":[0.1188426139],"iteration":902,"passed_time":4.073107496,"remaining_time":0.4375320344},
{"learn":[0.1187282615],"iteration":903,"passed_time":4.076657013,"remaining_time":0.4329193288},
{"learn":[0.1186881651],"iteration":904,"passed_time":4.08072828,"remaining_time":0.4283637421},
{"learn":[0.1185937146],"iteration":905,"passed_time":4.08445648,"remaining_time":0.4237736304},
{"learn":[0.1185025895],"iteration":906,"passed_time":4.087733161,"remaining_time":0.4191391224},
{"learn":[0.1184169898],"iteration":907,"passed_time":4.091519608,"remaining_time":0.4145592555},
{"learn":[0.1182773064],"iteration":908,"passed_time":4.095529263,"remaining_time":0.4100034796},
{"learn":[0.1182155703],"iteration":909,"passed_time":4.099916378,"remaining_time":0.4054862352},
{"learn":[0.1181488911],"iteration":910,"passed_time":4.103327895,"remaining_time":0.4008739656},
{"learn":[0.1179621967],"iteration":911,"passed_time":4.106511876,"remaining_time":0.396242374},
{"learn":[0.1176991893],"iteration":912,"passed_time":4.109782322,"remaining_time":0.3916221928},
{"learn":[0.1175245226],"iteration":913,"passed_time":4.113869382,"remaining_time":0.3870818019},
{"learn":[0.1173948995],"iteration":914,"passed_time":4.116994379,"remaining_time":0.3824530297},
{"learn":[0.1172944729],"iteration":915,"passed_time":4.120945115,"remaining_time":0.3779032638},
{"learn":[0.1172071818],"iteration":916,"passed_time":4.124360164,"remaining_time":0.373306318},
{"learn":[0.1170790928],"iteration":917,"passed_time":4.127570547,"remaining_time":0.3686936654},
{"learn":[0.1169850485],"iteration":918,"passed_time":4.131436072,"remaining_time":0.3641418083},
{"learn":[0.1168707009],"iteration":919,"passed_time":4.135200284,"remaining_time":0.3595826334},
{"learn":[0.1168012574],"iteration":920,"passed_time":4.13844581,"remaining_time":0.3549806938},
{"learn":[0.1167600104],"iteration":921,"passed_time":4.142511251,"remaining_time":0.3504510602},
{"learn":[0.1166462026],"iteration":922,"passed_time":4.145803648,"remaining_time":0.3458579425},
{"learn":[0.116562164],"iteration":923,"passed_time":4.148964117,"remaining_time":0.3412567888},
{"learn":[0.1164613761],"iteration":924,"passed_time":4.152640619,"remaining_time":0.3367005907},
{"learn":[0.1162409534],"iteration":925,"passed_time":4.15659733,"remaining_time":0.3321686851},
{"learn":[0.1161669],"iteration":926,"passed_time":4.162512658,"remaining_time":0.327792259},
{"learn":[0.1159981598],"iteration":927,"passed_time":4.166816544,"remaining_time":0.3232874905},
{"learn":[0.1159053059],"iteration":928,"passed_time":4.171540246,"remaining_time":0.3188152394},
{"learn":[0.1158117262],"iteration":929,"passed_time":4.177354848,"remaining_time":0.3144245585},
{"learn":[0.1157573024],"iteration":930,"passed_time":4.182507456,"remaining_time":0.3099817556},
{"learn":[0.1155288413],"iteration":931,"passed_time":4.186521844,"remaining_time":0.3054543835},
{"learn":[0.1154419793],"iteration":932,"passed_time":4.190941481,"remaining_time":0.3009572125},
{"learn":[0.1153895162],"iteration":933,"passed_time":4.194817036,"remaining_time":0.2964217605},
{"learn":[0.1153141729],"iteration":934,"passed_time":4.198297957,"remaining_time":0.2918602858},
{"learn":[0.1152057271],"iteration":935,"passed_time":4.202745457,"remaining_time":0.2873672107},
{"learn":[0.1151315582],"iteration":936,"passed_time":4.206847569,"remaining_time":0.2828510105},
{"learn":[0.1150392904],"iteration":937,"passed_time":4.210474911,"remaining_time":0.2783043118},
{"learn":[0.1149447113],"iteration":938,"passed_time":4.21469553,"remaining_time":0.2737981121},
{"learn":[0.1147962762],"iteration":939,"passed_time":4.218718213,"remaining_time":0.269279886},
{"learn":[0.1147535095],"iteration":940,"passed_time":4.222998378,"remaining_time":0.2647788568},
{"learn":[0.1146202995],"iteration":941,"passed_time":4.226919407,"remaining_time":0.2602561843},
{"learn":[0.1145277966],"iteration":942,"passed_time":4.230822703,"remaining_time":0.2557337159},
{"learn":[0.1143782444],"iteration":943,"passed_time":4.235026811,"remaining_time":0.251230404},
{"learn":[0.1142900822],"iteration":944,"passed_time":4.239790445,"remaining_time":0.2467602905},
{"learn":[0.1140595716],"iteration":945,"passed_time":4.243906752,"remaining_time":0.2422526053},
{"learn":[0.113942912],"iteration":946,"passed_time":4.249056273,"remaining_time":0.2378035718},
{"learn":[0.1138653263],"iteration":947,"passed_time":4.252931957,"remaining_time":0.2332831875},
{"learn":[0.1138320535],"iteration":948,"passed_time":4.257946796,"remaining_time":0.228825381},
{"learn":[0.1137551348],"iteration":949,"passed_time":4.262707077,"remaining_time":0.224353004},
{"learn":[0.1136657316],"iteration":950,"passed_time":4.267600054,"remaining_time":0.2198868587},
{"learn":[0.1135428395],"iteration":951,"passed_time":4.271707038,"remaining_time":0.2153801868},
{"learn":[0.11340145],"iteration":952,"passed_time":4.276606275,"remaining_time":0.2109134259},
{"learn":[0.1132729192],"iteration":953,"passed_time":4.280979489,"remaining_time":0.2064203946},
{"learn":[0.1132269684],"iteration":954,"passed_time":4.284701184,"remaining_time":0.2018969144},
{"learn":[0.1131816548],"iteration":955,"passed_time":4.288343802,"remaining_time":0.1973714721},
{"learn":[0.1130851805],"iteration":956,"passed_time":4.292150322,"remaining_time":0.1928552391},
{"learn":[0.112948888],"iteration":957,"passed_time":4.29656431,"remaining_time":0.1883671201},
{"learn":[0.1128013386],"iteration":958,"passed_time":4.300645987,"remaining_time":0.1838649483},
{"learn":[0.112711618],"iteration":959,"passed_time":4.304509307,"remaining_time":0.1793545545},
{"learn":[0.1126099562],"iteration":960,"passed_time":4.308132885,"remaining_time":0.1748357779},
{"learn":[0.1124990054],"iteration":961,"passed_time":4.311824474,"remaining_time":0.1703215489},
{"learn":[0.1123374507],"iteration":962,"passed_time":4.316528171,"remaining_time":0.1658479152},
{"learn":[0.1122512709],"iteration":963,"passed_time":4.32058199,"remaining_time":0.1613495349},
{"learn":[0.1122069142],"iteration":964,"passed_time":4.324488018,"remaining_time":0.1568467157},
{"learn":[0.1121304083],"iteration":965,"passed_time":4.328110995,"remaining_time":0.1523351696},
{"learn":[0.1120596821],"iteration":966,"passed_time":4.331696223,"remaining_time":0.1478241731},
{"learn":[0.1120292128],"iteration":967,"passed_time":4.335859253,"remaining_time":0.1433341902},
{"learn":[0.1119329509],"iteration":968,"passed_time":4.339760691,"remaining_time":0.1388365133},
{"learn":[0.1117818558],"iteration":969,"passed_time":4.345412336,"remaining_time":0.1343941959},
{"learn":[0.1116716648],"iteration":970,"passed_time":4.348951213,"remaining_time":0.1298862875},
{"learn":[0.1115730661],"iteration":971,"passed_time":4.352657154,"remaining_time":0.1253851855},
{"learn":[0.1114304767],"iteration":972,"passed_time":4.357405958,"remaining_time":0.1209146566},
{"learn":[0.1113535614],"iteration":973,"passed_time":4.361144572,"remaining_time":0.1164165902},
{"learn":[0.1112260505],"iteration":974,"passed_time":4.364849477,"remaining_time":0.1119192174},
{"learn":[0.111181491],"iteration":975,"passed_time":4.367827356,"remaining_time":0.1074055907},
{"learn":[0.1111036774],"iteration":976,"passed_time":4.371544032,"remaining_time":0.1029125002},
{"learn":[0.1110095518],"iteration":977,"passed_time":4.375168103,"remaining_time":0.09841891438},
{"learn":[0.1108830812],"iteration":978,"passed_time":4.378609072,"remaining_time":0.09392317724},
{"learn":[0.1106848799],"iteration":979,"passed_time":4.382851335,"remaining_time":0.08944594561},
{"learn":[0.110570817],"iteration":980,"passed_time":4.386690182,"remaining_time":0.08496137967},
{"learn":[0.1103907363],"iteration":981,"passed_time":4.390129393,"remaining_time":0.08047080353},
{"learn":[0.1102865732],"iteration":982,"passed_time":4.394924293,"remaining_time":0.07600581178},
{"learn":[0.1102141364],"iteration":983,"passed_time":4.398387216,"remaining_time":0.07151849132},
{"learn":[0.110121409],"iteration":984,"passed_time":4.402785829,"remaining_time":0.06704749993},
{"learn":[0.1100193685],"iteration":985,"passed_time":4.406273993,"remaining_time":0.0625637281},
{"learn":[0.1099599434],"iteration":986,"passed_time":4.409648017,"remaining_time":0.05808047034},
{"learn":[0.1099077921],"iteration":987,"passed_time":4.413363643,"remaining_time":0.053603607},
{"learn":[0.1098110764],"iteration":988,"passed_time":4.416824447,"remaining_time":0.04912544885},
{"learn":[0.109696078],"iteration":989,"passed_time":4.420382608,"remaining_time":0.04465032937},
{"learn":[0.1095899325],"iteration":990,"passed_time":4.423938954,"remaining_time":0.04017704398},
{"learn":[0.1095211914],"iteration":991,"passed_time":4.427638316,"remaining_time":0.03570676062},
{"learn":[0.1094266783],"iteration":992,"passed_time":4.430940401,"remaining_time":0.03123522941},
{"learn":[0.1093412071],"iteration":993,"passed_time":4.435741147,"remaining_time":0.02677509747},
{"learn":[0.1092458504],"iteration":994,"passed_time":4.439377419,"remaining_time":0.02230842924},
{"learn":[0.1091791421],"iteration":995,"passed_time":4.443973083,"remaining_time":0.01784728146},
{"learn":[0.109111787],"iteration":996,"passed_time":4.448603928,"remaining_time":0.01338596969},
{"learn":[0.1090143343],"iteration":997,"passed_time":4.454359662,"remaining_time":0.008926572469},
{"learn":[0.108929709],"iteration":998,"passed_time":4.458545155,"remaining_time":0.004463008163},
{"learn":[0.1088153254],"iteration":999,"passed_time":4.462070565,"remaining_time":0}
]}